Workbook

Sheet Controls
A2: Legacy ERP: | B2: Sage 300 CRE
A3: New ERP: | B3: Sage Intacct
A5: Field | B5: Value | C5: [MAP].[E_USEFUL_FIELDS]
A6: GL01_BALANCE_END | B6: 45657 | C6: ="UPDATE "&C$5&" SET FIELD_VALUE = '"&TEXT(B6,"YYYY-MM-DD")&"' WHERE FIELD_NAME = '"&A6&"'" -> UPDATE [MAP].[E_USEFUL_FIELDS] SET FIELD_VALUE = '2024-12-31' WHERE FIELD_NAME = 'GL01_BALANCE_END'
A7: GL02_MONTHLY_START | B7: 45658 | C7: ="UPDATE "&C$5&" SET FIELD_VALUE = '"&TEXT(B7,"YYYY-MM-DD")&"' WHERE FIELD_NAME = '"&A7&"'" -> UPDATE [MAP].[E_USEFUL_FIELDS] SET FIELD_VALUE = '2025-01-01' WHERE FIELD_NAME = 'GL02_MONTHLY_START'
A8: GL02_MONTHLY_STOP | B8: 46022 | C8: ="UPDATE "&C$5&" SET FIELD_VALUE = '"&TEXT(B8,"YYYY-MM-DD")&"' WHERE FIELD_NAME = '"&A8&"'" -> UPDATE [MAP].[E_USEFUL_FIELDS] SET FIELD_VALUE = '2025-12-31' WHERE FIELD_NAME = 'GL02_MONTHLY_STOP'
A9: GL03_DETAIL_START | B9: 46023 | C9: ="UPDATE "&C$5&" SET FIELD_VALUE = '"&TEXT(B9,"YYYY-MM-DD")&"' WHERE FIELD_NAME = '"&A9&"'" -> UPDATE [MAP].[E_USEFUL_FIELDS] SET FIELD_VALUE = '2026-01-01' WHERE FIELD_NAME = 'GL03_DETAIL_START'
A10: GL03_DETAIL_STOP | B10: 46081 | C10: ="UPDATE "&C$5&" SET FIELD_VALUE = '"&TEXT(B10,"YYYY-MM-DD")&"' WHERE FIELD_NAME = '"&A10&"'" -> UPDATE [MAP].[E_USEFUL_FIELDS] SET FIELD_VALUE = '2026-02-28' WHERE FIELD_NAME = 'GL03_DETAIL_STOP'

Sheet Entity
A1: ="Legacy ERP: "&Controls!$B$2 -> Legacy ERP: Sage 300 CRE | C1: ="New ERP: "&Controls!$B$3 -> New ERP: Sage Intacct
A3: Data Folder | B3: Data Folder Description | C3: Entity ID | D3: PKG_BASE | E3: PKG_CONSTR_SUM | F3: PKG_CONSTR_DET | G3: PKG_PAYROLL | H3: PKG_NPC_COMMIT | I3: PKG_PC_COMMIT | J3: [MAP].[T_TRANS_ENTITY] | K3: Change | L3: hide/show
A4: inter | C4: 100 | D4: 1 | E4: 1 | F4: 1 | G4: 0 | H4: 1 | I4: 0 | J4: ="UPDATE "&J$3&" SET NEW_ENTITY_ID = '"&TRIM(C4)&"', PKG_BASE = "&D4&", PKG_CONSTR_SUM = '"&E4&"', PKG_CONSTR_DET = '"&F4&"', PKG_PAYROLL = '"&G4&"', PKG_NPC_COMMIT = '"&H4&"', PKG_PC_COMMIT = '"&I4& "'"&" WHERE Data_Folder_Id = '"&A4&"'" -> UPDATE [MAP].[T_TRANS_ENTITY] SET NEW_ENTITY_ID = '100', PKG_BASE = 1, PKG_CONSTR_SUM = '1', PKG_CONSTR_DET = '1', PKG_PAYROLL = '0', PKG_NPC_COMMIT = '1', PKG_PC_COMMIT = '0' WHERE Data_Folder_Id = 'inter' | K4: =IF(A4<>C4,"Changed","-") -> Changed | L4: =IF(A4="","Hide","-") -> -
A5: paint | C5: 200 | D5: 1 | E5: 1 | F5: 1 | G5: 0 | H5: 0 | I5: 0 | J5: ="UPDATE "&J$3&" SET NEW_ENTITY_ID = '"&TRIM(C5)&"', PKG_BASE = "&D5&", PKG_CONSTR_SUM = '"&E5&"', PKG_CONSTR_DET = '"&F5&"', PKG_PAYROLL = '"&G5&"', PKG_NPC_COMMIT = '"&H5&"', PKG_PC_COMMIT = '"&I5& "'"&" WHERE Data_Folder_Id = '"&A5&"'" -> UPDATE [MAP].[T_TRANS_ENTITY] SET NEW_ENTITY_ID = '200', PKG_BASE = 1, PKG_CONSTR_SUM = '1', PKG_CONSTR_DET = '1', PKG_PAYROLL = '0', PKG_NPC_COMMIT = '0', PKG_PC_COMMIT = '0' WHERE Data_Folder_Id = 'paint' | K5: =IF(A5<>C5,"Changed","-") -> Changed | L5: =IF(A5="","Hide","-") -> -
A6: prem | C6: 300 | D6: 1 | E6: 1 | F6: 1 | G6: 0 | H6: 0 | I6: 0 | J6: ="UPDATE "&J$3&" SET NEW_ENTITY_ID = '"&TRIM(C6)&"', PKG_BASE = "&D6&", PKG_CONSTR_SUM = '"&E6&"', PKG_CONSTR_DET = '"&F6&"', PKG_PAYROLL = '"&G6&"', PKG_NPC_COMMIT = '"&H6&"', PKG_PC_COMMIT = '"&I6& "'"&" WHERE Data_Folder_Id = '"&A6&"'" -> UPDATE [MAP].[T_TRANS_ENTITY] SET NEW_ENTITY_ID = '300', PKG_BASE = 1, PKG_CONSTR_SUM = '1', PKG_CONSTR_DET = '1', PKG_PAYROLL = '0', PKG_NPC_COMMIT = '0', PKG_PC_COMMIT = '0' WHERE Data_Folder_Id = 'prem' | K6: =IF(A6<>C6,"Changed","-") -> Changed | L6: =IF(A6="","Hide","-") -> -

Sheet Job ID
A1: ="Legacy ERP: "&Controls!$B$2 -> Legacy ERP: Sage 300 CRE | E1: ="New ERP: "&Controls!$B$3 -> New ERP: Sage Intacct
A3: Data Folder ID | B3: Job | C3: Job Extra | D3: Job Description | E3: Include? | F3: Job | G3: Entity/Loc ID | H3: Department ID | I3: Class ID | J3: Customer ID | K3: PM ID | L3: [MAP].[T_TRANS_JOB] | M3: Change | N3: hide/show
A4: schi | B4: 14-117 | D4: Laceworks CM Project | E4: Yes | F4: Test001 | G4: PA | H4: Commercial | I4: CM | J4: C0056 | K4: 10024 | L4: ="UPDATE "&L$3&" SET NEW_JOB_ID = '"&TRIM(F4)&"', INCLUDE_JOB = "&IF(E4="Yes",1,0)&", NEW_ENTITY_ID = '"&G4&"', NEW_DEPARTMENT_ID = '"&H4&"', NEW_CLASS_ID = '"&I4&"', NEW_CUSTOMER_ID = '"&J4&"', NEW_PM_ID = '"&K4& "'"&" WHERE LEGACY_JOB_ID = '"&TRIM(B4)&"' AND Data_Folder_Id = '"&A4&"'" -> UPDATE [MAP].[T_TRANS_JOB] SET NEW_JOB_ID = 'Test001', INCLUDE_JOB = 1, NEW_ENTITY_ID = 'PA', NEW_DEPARTMENT_ID = 'Commercial', NEW_CLASS_ID = 'CM', NEW_CUSTOMER_ID = 'C0056', NEW_PM_ID = '10024' WHERE LEGACY_JOB_ID = '14-117' AND Data_Folder_Id = 'schi' | M4: =IF(B4<>F4,"Changed","-") -> Changed | N4: =IF(B4="","Hide","-") -> -
A5: schi | B5: 16-599 | D5: Laceworks Pennvest Storm Water | E5: Yes | F5: Test002 | G5: PA | H5: Commercial | I5: CM | J5: C0056 | K5: 10024 | L5: ="UPDATE "&L$3&" SET NEW_JOB_ID = '"&TRIM(F5)&"', INCLUDE_JOB = "&IF(E5="Yes",1,0)&", NEW_ENTITY_ID = '"&G5&"', NEW_DEPARTMENT_ID = '"&H5&"', NEW_CLASS_ID = '"&I5&"', NEW_CUSTOMER_ID = '"&J5&"', NEW_PM_ID = '"&K5& "'"&" WHERE LEGACY_JOB_ID = '"&TRIM(B5)&"' AND Data_Folder_Id = '"&A5&"'" -> UPDATE [MAP].[T_TRANS_JOB] SET NEW_JOB_ID = 'Test002', INCLUDE_JOB = 1, NEW_ENTITY_ID = 'PA', NEW_DEPARTMENT_ID = 'Commercial', NEW_CLASS_ID = 'CM', NEW_CUSTOMER_ID = 'C0056', NEW_PM_ID = '10024' WHERE LEGACY_JOB_ID = '16-599' AND Data_Folder_Id = 'schi' | M5: =IF(B5<>F5,"Changed","-") -> Changed | N5: =IF(B5="","Hide","-") -> -
A6: schi | B6: 17-005 | D6: COLTS Transit Facility | E6: Yes | F6: Test003 | G6: PA | H6: Commercial | I6: GC | J6: C0022 | K6: 10046 | L6: ="UPDATE "&L$3&" SET NEW_JOB_ID = '"&TRIM(F6)&"', INCLUDE_JOB = "&IF(E6="Yes",1,0)&", NEW_ENTITY_ID = '"&G6&"', NEW_DEPARTMENT_ID = '"&H6&"', NEW_CLASS_ID = '"&I6&"', NEW_CUSTOMER_ID = '"&J6&"', NEW_PM_ID = '"&K6& "'"&" WHERE LEGACY_JOB_ID = '"&TRIM(B6)&"' AND Data_Folder_Id = '"&A6&"'" -> UPDATE [MAP].[T_TRANS_JOB] SET NEW_JOB_ID = 'Test003', INCLUDE_JOB = 1, NEW_ENTITY_ID = 'PA', NEW_DEPARTMENT_ID = 'Commercial', NEW_CLASS_ID = 'GC', NEW_CUSTOMER_ID = 'C0022', NEW_PM_ID = '10046' WHERE LEGACY_JOB_ID = '17-005' AND Data_Folder_Id = 'schi' | M6: =IF(B6<>F6,"Changed","-") -> Changed | N6: =IF(B6="","Hide","-") -> -
A7: schi | B7: 17-101 | D7: Fidelity Bank Corporate HQ | E7: Yes | F7: Test004 | G7: PA | H7: Commercial | I7: CM | J7: C0035 | K7: 10015 | L7: ="UPDATE "&L$3&" SET NEW_JOB_ID = '"&TRIM(F7)&"', INCLUDE_JOB = "&IF(E7="Yes",1,0)&", NEW_ENTITY_ID = '"&G7&"', NEW_DEPARTMENT_ID = '"&H7&"', NEW_CLASS_ID = '"&I7&"', NEW_CUSTOMER_ID = '"&J7&"', NEW_PM_ID = '"&K7& "'"&" WHERE LEGACY_JOB_ID = '"&TRIM(B7)&"' AND Data_Folder_Id = '"&A7&"'" -> UPDATE [MAP].[T_TRANS_JOB] SET NEW_JOB_ID = 'Test004', INCLUDE_JOB = 1, NEW_ENTITY_ID = 'PA', NEW_DEPARTMENT_ID = 'Commercial', NEW_CLASS_ID = 'CM', NEW_CUSTOMER_ID = 'C0035', NEW_PM_ID = '10015' WHERE LEGACY_JOB_ID = '17-101' AND Data_Folder_Id = 'schi' | M7: =IF(B7<>F7,"Changed","-") -> Changed | N7: =IF(B7="","Hide","-") -> -

Sheet GL Account
A1: ="Legacy ERP: "&Controls!$B$2 -> Legacy ERP: Sage 300 CRE | D1: ="New ERP: "&Controls!$B$3 -> New ERP: Sage Intacct
A3: Data Folder ID | B3: GL Account | C3: GL Account Description | D3: GL Account | E3: [MAP].[T_TRANS_BASEACCT] | F3: Change | G3: hide/show
A4: sampl | B4: 1000 | C4: Cash - Petty Cash | D4: 1000 | E4: ="UPDATE "&$E$3&" SET New_Base_Account = '"&D4&"' WHERE Legacy_Base_Account = '"&B4&"' AND Data_Folder_Id = '"&$A4&"'" -> UPDATE [MAP].[T_TRANS_BASEACCT] SET New_Base_Account = '1000' WHERE Legacy_Base_Account = '1000' AND Data_Folder_Id = 'sampl' | F4: =IF(B4<>D4,"Changed","-") -> - | G4: =IF(B4="","Hide","-") -> -
A5: sampl | B5: 1005 | C5: Cash - Fidelity Operations | D5: 1005 | E5: ="UPDATE "&$E$3&" SET New_Base_Account = '"&D5&"' WHERE Legacy_Base_Account = '"&B5&"' AND Data_Folder_Id = '"&$A5&"'" -> UPDATE [MAP].[T_TRANS_BASEACCT] SET New_Base_Account = '1005' WHERE Legacy_Base_Account = '1005' AND Data_Folder_Id = 'sampl' | F5: =IF(B5<>D5,"Changed","-") -> - | G5: =IF(B5="","Hide","-") -> -

Sheet Location ID
A1: ="Legacy ERP: "&Controls!$B$2 -> Legacy ERP: Sage 300 CRE | D1: ="New ERP: "&Controls!$B$3 -> New ERP: Sage Intacct
A3: Data Folder ID | B3: Location | C3: Location Description | D3: Location | E3: [MAP].[T_TRANS_LOCATION] | F3: Change | G3: hide/show
A4: sampl | B4: 1-00 | C4: 1-00 LRC Balance Sheet | D4: E010 | E4: ="UPDATE "&$E$3&" SET New_Location_Id = '"&D4&"' WHERE Legacy_Location_Id = '"&B4&"' AND Data_Folder_Id = '"&$A4&"'" -> UPDATE [MAP].[T_TRANS_LOCATION] SET New_Location_Id = 'E010' WHERE Legacy_Location_Id = '1-00' AND Data_Folder_Id = 'sampl' | F4: =IF(B4<>D4,"Changed","-") -> Changed | G4: =IF(B4="","Hide","-") -> -
A5: sampl | B5: 1-88 | C5: 1-88 Corporate | D5: CO | E5: ="UPDATE "&$E$3&" SET New_Location_Id = '"&D5&"' WHERE Legacy_Location_Id = '"&B5&"' AND Data_Folder_Id = '"&$A5&"'" -> UPDATE [MAP].[T_TRANS_LOCATION] SET New_Location_Id = 'CO' WHERE Legacy_Location_Id = '1-88' AND Data_Folder_Id = 'sampl' | F5: =IF(B5<>D5,"Changed","-") -> Changed | G5: =IF(B5="","Hide","-") -> -
A6: sampl | B6: 1-20 | C6: 1-20 New Jersey | D6: NJ | E6: ="UPDATE "&$E$3&" SET New_Location_Id = '"&D6&"' WHERE Legacy_Location_Id = '"&B6&"' AND Data_Folder_Id = '"&$A6&"'" -> UPDATE [MAP].[T_TRANS_LOCATION] SET New_Location_Id = 'NJ' WHERE Legacy_Location_Id = '1-20' AND Data_Folder_Id = 'sampl' | F6: =IF(B6<>D6,"Changed","-") -> Changed | G6: =IF(B6="","Hide","-") -> -
A7: sampl | B7: 1-25 | C7: 1-25 Other | D7: OT | E7: ="UPDATE "&$E$3&" SET New_Location_Id = '"&D7&"' WHERE Legacy_Location_Id = '"&B7&"' AND Data_Folder_Id = '"&$A7&"'" -> UPDATE [MAP].[T_TRANS_LOCATION] SET New_Location_Id = 'OT' WHERE Legacy_Location_Id = '1-25' AND Data_Folder_Id = 'sampl' | F7: =IF(B7<>D7,"Changed","-") -> Changed | G7: =IF(B7="","Hide","-") -> -
A8: sampl | B8: 1-10 | C8: 1-10 Pennsylvania | D8: PA | E8: ="UPDATE "&$E$3&" SET New_Location_Id = '"&D8&"' WHERE Legacy_Location_Id = '"&B8&"' AND Data_Folder_Id = '"&$A8&"'" -> UPDATE [MAP].[T_TRANS_LOCATION] SET New_Location_Id = 'PA' WHERE Legacy_Location_Id = '1-10' AND Data_Folder_Id = 'sampl' | F8: =IF(B8<>D8,"Changed","-") -> Changed | G8: =IF(B8="","Hide","-") -> -
A9: sampl | B9: 1-15 | C9: 1-15 West Virginia | D9: WV | E9: ="UPDATE "&$E$3&" SET New_Location_Id = '"&D9&"' WHERE Legacy_Location_Id = '"&B9&"' AND Data_Folder_Id = '"&$A9&"'" -> UPDATE [MAP].[T_TRANS_LOCATION] SET New_Location_Id = 'WV' WHERE Legacy_Location_Id = '1-15' AND Data_Folder_Id = 'sampl' | F9: =IF(B9<>D9,"Changed","-") -> Changed | G9: =IF(B9="","Hide","-") -> -
A10: sampl | B10: 1-99 | C10: 1-99 SUSPENSE | E10: ="UPDATE "&$E$3&" SET New_Location_Id = '"&D10&"' WHERE Legacy_Location_Id = '"&B10&"' AND Data_Folder_Id = '"&$A10&"'" -> UPDATE [MAP].[T_TRANS_LOCATION] SET New_Location_Id = '' WHERE Legacy_Location_Id = '1-99' AND Data_Folder_Id = 'sampl' | F10: =IF(B10<>D10,"Changed","-") -> Changed | G10: =IF(B10="","Hide","-") -> -

Sheet Department ID
A1: ="Legacy ERP: "&Controls!$B$2 -> Legacy ERP: Sage 300 CRE | D1: ="New ERP: "&Controls!$B$3 -> New ERP: Sage Intacct
A3: Data Folder ID | B3: Department | C3: Department Description | D3: Department | E3: [MAP].[T_TRANS_DEPARTMENT] | F3: Change | G3: hide/show
A4: sampl | D4: E010 | E4: ="UPDATE "&$E$3&" SET New_Department_Id = '"&D4&"' WHERE Legacy_Department_Id = '"&B4&"' AND Data_Folder_Id = '"&$A4&"'" -> UPDATE [MAP].[T_TRANS_DEPARTMENT] SET New_Department_Id = 'E010' WHERE Legacy_Department_Id = '' AND Data_Folder_Id = 'sampl' | F4: =IF(B4<>D4,"Changed","-") -> Changed | G4: =IF(B4="","Hide","-") -> Hide
A5: sampl | D5: CO | E5: ="UPDATE "&$E$3&" SET New_Department_Id = '"&D5&"' WHERE Legacy_Department_Id = '"&B5&"' AND Data_Folder_Id = '"&$A5&"'" -> UPDATE [MAP].[T_TRANS_DEPARTMENT] SET New_Department_Id = 'CO' WHERE Legacy_Department_Id = '' AND Data_Folder_Id = 'sampl' | F5: =IF(A5<>B5,"Changed","-") -> Changed | G5: =IF(B5="","Hide","-") -> Hide
A6: sampl | D6: NJ | E6: ="UPDATE "&$E$3&" SET New_Department_Id = '"&D6&"' WHERE Legacy_Department_Id = '"&B6&"' AND Data_Folder_Id = '"&$A6&"'" -> UPDATE [MAP].[T_TRANS_DEPARTMENT] SET New_Department_Id = 'NJ' WHERE Legacy_Department_Id = '' AND Data_Folder_Id = 'sampl' | F6: =IF(A6<>B6,"Changed","-") -> Changed | G6: =IF(B6="","Hide","-") -> Hide
A7: sampl | D7: OT | E7: ="UPDATE "&$E$3&" SET New_Department_Id = '"&D7&"' WHERE Legacy_Department_Id = '"&B7&"' AND Data_Folder_Id = '"&$A7&"'" -> UPDATE [MAP].[T_TRANS_DEPARTMENT] SET New_Department_Id = 'OT' WHERE Legacy_Department_Id = '' AND Data_Folder_Id = 'sampl' | F7: =IF(A7<>B7,"Changed","-") -> Changed | G7: =IF(B7="","Hide","-") -> Hide

Sheet Class ID
A1: ="Legacy ERP: "&Controls!$B$2 -> Legacy ERP: Sage 300 CRE | D1: ="New ERP: "&Controls!$B$3 -> New ERP: Sage Intacct
A3: Data Folder ID | B3: Class | C3: Class Description | D3: Class | E3: [MAP].[T_TRANS_CLASS] | F3: Change | G3: hide/show
A4: sampl | B4: 330MONTAGE | C4: 330 Montage Mountain Road LLC | D4: V0002 | E4: ="UPDATE "&$E$3&" SET NEW_CLASS_ID = '"&D4&"' WHERE LEGACY_CLASS_ID = '"&B4&"' AND DATA_FOLDER_ID = '"&$A4&"'" -> UPDATE [MAP].[T_TRANS_CLASS] SET NEW_CLASS_ID = 'V0002' WHERE LEGACY_CLASS_ID = '330MONTAGE' AND DATA_FOLDER_ID = 'sampl' | F4: =IF(B4<>D4,"Changed","-") -> Changed | G4: =IF(B4="","Hide","-") -> -
A5: sampl | B5: 84LUMBER | C5: 84 Lumber | D5: V0003 | E5: ="UPDATE "&$E$3&" SET NEW_CLASS_ID = '"&D5&"' WHERE LEGACY_CLASS_ID = '"&B5&"' AND DATA_FOLDER_ID = '"&$A5&"'" -> UPDATE [MAP].[T_TRANS_CLASS] SET NEW_CLASS_ID = 'V0003' WHERE LEGACY_CLASS_ID = '84LUMBER' AND DATA_FOLDER_ID = 'sampl' | F5: =IF(B5<>D5,"Changed","-") -> Changed | G5: =IF(B5="","Hide","-") -> -

Sheet Vendor ID
A1: ="Legacy ERP: "&Controls!$B$2 -> Legacy ERP: Sage 300 CRE | D1: ="New ERP: "&Controls!$B$3 -> New ERP: Sage Intacct
A3: Data Folder ID | B3: Vendor | C3: Vendor Description | D3: Vendor | E3: [MAP].[T_TRANS_VENDOR] | F3: Change | G3: hide/show
A4: sampl | B4: 330MONTAGE | C4: 330 Montage Mountain Road LLC | D4: V0002 | E4: ="UPDATE "&$E$3&" SET NEW_VENDOR_ID = '"&D4&"' WHERE LEGACY_VENDOR_ID = '"&B4&"' AND DATA_FOLDER_ID = '"&$A4&"'" -> UPDATE [MAP].[T_TRANS_VENDOR] SET NEW_VENDOR_ID = 'V0002' WHERE LEGACY_VENDOR_ID = '330MONTAGE' AND DATA_FOLDER_ID = 'sampl' | F4: =IF(B4<>D4,"Changed","-") -> Changed | G4: =IF(B4="","Hide","-") -> -
A5: sampl | B5: 84LUMBER | C5: 84 Lumber | D5: V0003 | E5: ="UPDATE "&$E$3&" SET NEW_VENDOR_ID = '"&D5&"' WHERE LEGACY_VENDOR_ID = '"&B5&"' AND DATA_FOLDER_ID = '"&$A5&"'" -> UPDATE [MAP].[T_TRANS_VENDOR] SET NEW_VENDOR_ID = 'V0003' WHERE LEGACY_VENDOR_ID = '84LUMBER' AND DATA_FOLDER_ID = 'sampl' | F5: =IF(B5<>D5,"Changed","-") -> Changed | G5: =IF(B5="","Hide","-") -> -
A6: sampl | B6: A&AAUTOP | C6: A&A Auto Parts Stores Inc | D6: V0004 | E6: ="UPDATE "&$E$3&" SET NEW_VENDOR_ID = '"&D6&"' WHERE LEGACY_VENDOR_ID = '"&B6&"' AND DATA_FOLDER_ID = '"&$A6&"'" -> UPDATE [MAP].[T_TRANS_VENDOR] SET NEW_VENDOR_ID = 'V0004' WHERE LEGACY_VENDOR_ID = 'A&AAUTOP' AND DATA_FOLDER_ID = 'sampl' | F6: =IF(B6<>D6,"Changed","-") -> Changed | G6: =IF(B6="","Hide","-") -> -
A7: sampl | B7: A&BDOORI | C7: A&B Door Sales & Service | D7: V0005 | E7: ="UPDATE "&$E$3&" SET NEW_VENDOR_ID = '"&D7&"' WHERE LEGACY_VENDOR_ID = '"&B7&"' AND DATA_FOLDER_ID = '"&$A7&"'" -> UPDATE [MAP].[T_TRANS_VENDOR] SET NEW_VENDOR_ID = 'V0005' WHERE LEGACY_VENDOR_ID = 'A&BDOORI' AND DATA_FOLDER_ID = 'sampl' | F7: =IF(B7<>D7,"Changed","-") -> Changed | G7: =IF(B7="","Hide","-") -> -
A8: sampl | B8: ABBINC | C8: ABB Inc | D8: V0006 | E8: ="UPDATE "&$E$3&" SET NEW_VENDOR_ID = '"&D8&"' WHERE LEGACY_VENDOR_ID = '"&B8&"' AND DATA_FOLDER_ID = '"&$A8&"'" -> UPDATE [MAP].[T_TRANS_VENDOR] SET NEW_VENDOR_ID = 'V0006' WHERE LEGACY_VENDOR_ID = 'ABBINC' AND DATA_FOLDER_ID = 'sampl' | F8: =IF(B8<>D8,"Changed","-") -> Changed | G8: =IF(B8="","Hide","-") -> -
A9: sampl | B9: ABCSUPPL | C9: ABC Supply Co Inc | D9: V0007 | E9: ="UPDATE "&$E$3&" SET NEW_VENDOR_ID = '"&D9&"' WHERE LEGACY_VENDOR_ID = '"&B9&"' AND DATA_FOLDER_ID = '"&$A9&"'" -> UPDATE [MAP].[T_TRANS_VENDOR] SET NEW_VENDOR_ID = 'V0007' WHERE LEGACY_VENDOR_ID = 'ABCSUPPL' AND DATA_FOLDER_ID = 'sampl' | F9: =IF(B9<>D9,"Changed","-") -> Changed | G9: =IF(B9="","Hide","-") -> -
A10: sampl | B10: ACCORDAN | C10: Accordant Company LLC | D10: V0008 | E10: ="UPDATE "&$E$3&" SET NEW_VENDOR_ID = '"&D10&"' WHERE LEGACY_VENDOR_ID = '"&B10&"' AND DATA_FOLDER_ID = '"&$A10&"'" -> UPDATE [MAP].[T_TRANS_VENDOR] SET NEW_VENDOR_ID = 'V0008' WHERE LEGACY_VENDOR_ID = 'ACCORDAN' AND DATA_FOLDER_ID = 'sampl' | F10: =IF(B10<>D10,"Changed","-") -> Changed | G10: =IF(B10="","Hide","-") -> -
A11: sampl | B11: acculock | C11: Accurate Locksmith | D11: V0009 | E11: ="UPDATE "&$E$3&" SET NEW_VENDOR_ID = '"&D11&"' WHERE LEGACY_VENDOR_ID = '"&B11&"' AND DATA_FOLDER_ID = '"&$A11&"'" -> UPDATE [MAP].[T_TRANS_VENDOR] SET NEW_VENDOR_ID = 'V0009' WHERE LEGACY_VENDOR_ID = 'acculock' AND DATA_FOLDER_ID = 'sampl' | F11: =IF(B11<>D11,"Changed","-") -> Changed | G11: =IF(B11="","Hide","-") -> -
A12: sampl | B12: ACOUSTIC | C12: ACOUSTICAL SPRAY INSULATION | D12: V0010 | E12: ="UPDATE "&$E$3&" SET NEW_VENDOR_ID = '"&D12&"' WHERE LEGACY_VENDOR_ID = '"&B12&"' AND DATA_FOLDER_ID = '"&$A12&"'" -> UPDATE [MAP].[T_TRANS_VENDOR] SET NEW_VENDOR_ID = 'V0010' WHERE LEGACY_VENDOR_ID = 'ACOUSTIC' AND DATA_FOLDER_ID = 'sampl' | F12: =IF(B12<>D12,"Changed","-") -> Changed | G12: =IF(B12="","Hide","-") -> -
A13: sampl | B13: ACSI0000 | C13: Air Cleaning Systems, Inc. | D13: V0011 | E13: ="UPDATE "&$E$3&" SET NEW_VENDOR_ID = '"&D13&"' WHERE LEGACY_VENDOR_ID = '"&B13&"' AND DATA_FOLDER_ID = '"&$A13&"'" -> UPDATE [MAP].[T_TRANS_VENDOR] SET NEW_VENDOR_ID = 'V0011' WHERE LEGACY_VENDOR_ID = 'ACSI0000' AND DATA_FOLDER_ID = 'sampl' | F13: =IF(B13<>D13,"Changed","-") -> Changed | G13: =IF(B13="","Hide","-") -> -
A14: sampl | B14: ACTADAMS | C14: Action Adam Services | D14: V0012 | E14: ="UPDATE "&$E$3&" SET NEW_VENDOR_ID = '"&D14&"' WHERE LEGACY_VENDOR_ID = '"&B14&"' AND DATA_FOLDER_ID = '"&$A14&"'" -> UPDATE [MAP].[T_TRANS_VENDOR] SET NEW_VENDOR_ID = 'V0012' WHERE LEGACY_VENDOR_ID = 'ACTADAMS' AND DATA_FOLDER_ID = 'sampl' | F14: =IF(B14<>D14,"Changed","-") -> Changed | G14: =IF(B14="","Hide","-") -> -
A15: sampl | B15: ACTIONLI | C15: Action Lift Inc | D15: V0013 | E15: ="UPDATE "&$E$3&" SET NEW_VENDOR_ID = '"&D15&"' WHERE LEGACY_VENDOR_ID = '"&B15&"' AND DATA_FOLDER_ID = '"&$A15&"'" -> UPDATE [MAP].[T_TRANS_VENDOR] SET NEW_VENDOR_ID = 'V0013' WHERE LEGACY_VENDOR_ID = 'ACTIONLI' AND DATA_FOLDER_ID = 'sampl' | F15: =IF(B15<>D15,"Changed","-") -> Changed | G15: =IF(B15="","Hide","-") -> -
... A1005: sampl | B1005: ABSTEEL | C1005: AB Steel | D1005: V1043 | E1005: ="UPDATE "&$E$3&" SET NEW_VENDOR_ID = '"&D1005&"' WHERE LEGACY_VENDOR_ID = '"&B1005&"' AND DATA_FOLDER_ID = '"&$A1005&"'" -> UPDATE [MAP].[T_TRANS_VENDOR] SET NEW_VENDOR_ID = 'V1043' WHERE LEGACY_VENDOR_ID = 'ABSTEEL' AND DATA_FOLDER_ID = 'sampl' | F1005: =IF(B1005<>D1005,"Changed","-") -> Changed | G1005: =IF(B1005="","Hide","-") -> -

Sheet Customer ID
A1: ="Legacy ERP: "&Controls!$B$2 -> Legacy ERP: Sage 300 CRE | D1: ="New ERP: "&Controls!$B$3 -> New ERP: Sage Intacct
A3: Data Folder ID | B3: Customer | C3: Customer Description | D3: Customer | E3: [MAP].[T_TRANS_CUSTOMER] | F3: Change | G3: hide/show
A4: sampl | B4: 330Monta | C4: 330 Montage Mountain Road LLC | D4: C0001 | E4: ="UPDATE "&$E$3&" SET NEW_CUSTOMER_ID = '"&D4&"' WHERE LEGACY_CUSTOMER_ID = '"&B4&"' AND DATA_FOLDER_ID = '"&$A4&"'" -> UPDATE [MAP].[T_TRANS_CUSTOMER] SET NEW_CUSTOMER_ID = 'C0001' WHERE LEGACY_CUSTOMER_ID = '330Monta' AND DATA_FOLDER_ID = 'sampl' | F4: =IF(B4<>D4,"Changed","-") -> Changed | G4: =IF(B4="","Hide","-") -> -
A5: sampl | B5: ADAPTIMM | C5: Adaptimmune LLC | D5: C0002 | E5: ="UPDATE "&$E$3&" SET NEW_CUSTOMER_ID = '"&D5&"' WHERE LEGACY_CUSTOMER_ID = '"&B5&"' AND DATA_FOLDER_ID = '"&$A5&"'" -> UPDATE [MAP].[T_TRANS_CUSTOMER] SET NEW_CUSTOMER_ID = 'C0002' WHERE LEGACY_CUSTOMER_ID = 'ADAPTIMM' AND DATA_FOLDER_ID = 'sampl' | F5: =IF(B5<>D5,"Changed","-") -> Changed | G5: =IF(B5="","Hide","-") -> -
A6: sampl | B6: ALTASCIE | C6: Altasciences Pre-Clinical Scranton | D6: C0003 | E6: ="UPDATE "&$E$3&" SET NEW_CUSTOMER_ID = '"&D6&"' WHERE LEGACY_CUSTOMER_ID = '"&B6&"' AND DATA_FOLDER_ID = '"&$A6&"'" -> UPDATE [MAP].[T_TRANS_CUSTOMER] SET NEW_CUSTOMER_ID = 'C0003' WHERE LEGACY_CUSTOMER_ID = 'ALTASCIE' AND DATA_FOLDER_ID = 'sampl' | F6: =IF(B6<>D6,"Changed","-") -> Changed | G6: =IF(B6="","Hide","-") -> -
A7: sampl | B7: AMERICAN | C7: American Custom Drying | D7: C0004 | E7: ="UPDATE "&$E$3&" SET NEW_CUSTOMER_ID = '"&D7&"' WHERE LEGACY_CUSTOMER_ID = '"&B7&"' AND DATA_FOLDER_ID = '"&$A7&"'" -> UPDATE [MAP].[T_TRANS_CUSTOMER] SET NEW_CUSTOMER_ID = 'C0004' WHERE LEGACY_CUSTOMER_ID = 'AMERICAN' AND DATA_FOLDER_ID = 'sampl' | F7: =IF(B7<>D7,"Changed","-") -> Changed | G7: =IF(B7="","Hide","-") -> -
A8: sampl | B8: AUTOTECH | C8: Autotech Concrete | D8: C0005 | E8: ="UPDATE "&$E$3&" SET NEW_CUSTOMER_ID = '"&D8&"' WHERE LEGACY_CUSTOMER_ID = '"&B8&"' AND DATA_FOLDER_ID = '"&$A8&"'" -> UPDATE [MAP].[T_TRANS_CUSTOMER] SET NEW_CUSTOMER_ID = 'C0005' WHERE LEGACY_CUSTOMER_ID = 'AUTOTECH' AND DATA_FOLDER_ID = 'sampl' | F8: =IF(B8<>D8,"Changed","-") -> Changed | G8: =IF(B8="","Hide","-") -> -
A9: sampl | B9: AVPQTA00 | C9: AVP QTA, LLC | D9: C0006 | E9: ="UPDATE "&$E$3&" SET NEW_CUSTOMER_ID = '"&D9&"' WHERE LEGACY_CUSTOMER_ID = '"&B9&"' AND DATA_FOLDER_ID = '"&$A9&"'" -> UPDATE [MAP].[T_TRANS_CUSTOMER] SET NEW_CUSTOMER_ID = 'C0006' WHERE LEGACY_CUSTOMER_ID = 'AVPQTA00' AND DATA_FOLDER_ID = 'sampl' | F9: =IF(B9<>D9,"Changed","-") -> Changed | G9: =IF(B9="","Hide","-") -> -
A10: sampl | B10: BALLCORP | C10: Ball Corporation | D10: C0007 | E10: ="UPDATE "&$E$3&" SET NEW_CUSTOMER_ID = '"&D10&"' WHERE LEGACY_CUSTOMER_ID = '"&B10&"' AND DATA_FOLDER_ID = '"&$A10&"'" -> UPDATE [MAP].[T_TRANS_CUSTOMER] SET NEW_CUSTOMER_ID = 'C0007' WHERE LEGACY_CUSTOMER_ID = 'BALLCORP' AND DATA_FOLDER_ID = 'sampl' | F10: =IF(B10<>D10,"Changed","-") -> Changed | G10: =IF(B10="","Hide","-") -> -
A11: sampl | B11: BEDACOMP | C11: BEDA Company Inc | D11: C0008 | E11: ="UPDATE "&$E$3&" SET NEW_CUSTOMER_ID = '"&D11&"' WHERE LEGACY_CUSTOMER_ID = '"&B11&"' AND DATA_FOLDER_ID = '"&$A11&"'" -> UPDATE [MAP].[T_TRANS_CUSTOMER] SET NEW_CUSTOMER_ID = 'C0008' WHERE LEGACY_CUSTOMER_ID = 'BEDACOMP' AND DATA_FOLDER_ID = 'sampl' | F11: =IF(B11<>D11,"Changed","-") -> Changed | G11: =IF(B11="","Hide","-") -> -
A12: sampl | B12: BEINKE | C12: FR Beinke Wrecking Inc | D12: C0009 | E12: ="UPDATE "&$E$3&" SET NEW_CUSTOMER_ID = '"&D12&"' WHERE LEGACY_CUSTOMER_ID = '"&B12&"' AND DATA_FOLDER_ID = '"&$A12&"'" -> UPDATE [MAP].[T_TRANS_CUSTOMER] SET NEW_CUSTOMER_ID = 'C0009' WHERE LEGACY_CUSTOMER_ID = 'BEINKE' AND DATA_FOLDER_ID = 'sampl' | F12: =IF(B12<>D12,"Changed","-") -> Changed | G12: =IF(B12="","Hide","-") -> -
A13: sampl | B13: BILFINGE | C13: Bilfinger Industrial Services | D13: C0010 | E13: ="UPDATE "&$E$3&" SET NEW_CUSTOMER_ID = '"&D13&"' WHERE LEGACY_CUSTOMER_ID = '"&B13&"' AND DATA_FOLDER_ID = '"&$A13&"'" -> UPDATE [MAP].[T_TRANS_CUSTOMER] SET NEW_CUSTOMER_ID = 'C0010' WHERE LEGACY_CUSTOMER_ID = 'BILFINGE' AND DATA_FOLDER_ID = 'sampl' | F13: =IF(B13<>D13,"Changed","-") -> Changed | G13: =IF(B13="","Hide","-") -> -
A14: sampl | B14: BMPROPTY | C14: B&M Property Development LLC | D14: C0011 | E14: ="UPDATE "&$E$3&" SET NEW_CUSTOMER_ID = '"&D14&"' WHERE LEGACY_CUSTOMER_ID = '"&B14&"' AND DATA_FOLDER_ID = '"&$A14&"'" -> UPDATE [MAP].[T_TRANS_CUSTOMER] SET NEW_CUSTOMER_ID = 'C0011' WHERE LEGACY_CUSTOMER_ID = 'BMPROPTY' AND DATA_FOLDER_ID = 'sampl' | F14: =IF(B14<>D14,"Changed","-") -> Changed | G14: =IF(B14="","Hide","-") -> -
A15: sampl | B15: BORTONLA | C15: Verdantas LLC | D15: C0012 | E15: ="UPDATE "&$E$3&" SET NEW_CUSTOMER_ID = '"&D15&"' WHERE LEGACY_CUSTOMER_ID = '"&B15&"' AND DATA_FOLDER_ID = '"&$A15&"'" -> UPDATE [MAP].[T_TRANS_CUSTOMER] SET NEW_CUSTOMER_ID = 'C0012' WHERE LEGACY_CUSTOMER_ID = 'BORTONLA' AND DATA_FOLDER_ID = 'sampl' | F15: =IF(B15<>D15,"Changed","-") -> Changed | G15: =IF(B15="","Hide","-") -> -
... A126: sampl | B126: MILLTOWN | C126: Milltown Onsite Generation LLC | D126: C0123 | E126: ="UPDATE "&$E$3&" SET NEW_CUSTOMER_ID = '"&D126&"' WHERE LEGACY_CUSTOMER_ID = '"&B126&"' AND DATA_FOLDER_ID = '"&$A126&"'" -> UPDATE [MAP].[T_TRANS_CUSTOMER] SET NEW_CUSTOMER_ID = 'C0123' WHERE LEGACY_CUSTOMER_ID = 'MILLTOWN' AND DATA_FOLDER_ID = 'sampl' | F126: =IF(B126<>D126,"Changed","-") -> Changed | G126: =IF(B126="","Hide","-") -> -

Sheet Cost Code ID
A1: ="Legacy ERP: "&Controls!$B$2 -> Legacy ERP: Sage 300 CRE | D1: ="New ERP: "&Controls!$B$3 -> New ERP: Sage Intacct
A3: Data Folder ID | B3: Cost Code | C3: Cost Code Description | D3: Cost Code | E3: Item ID | F3: [MAP].[T_TRANS_COST_CODE] | G3: Change | H3: hide/show
A4: sampl | B4: 01-0000 | C4: GENERAL REQUIREMENTS | D4: 01-0000 | F4: ="UPDATE "&F$3&" SET NEW_COST_CODE_ID = '"&D4&"', NEW_ITEM_ID = '"&E4&"' WHERE LEGACY_COST_CODE_ID = '"&B4&"' AND DATA_FOLDER_ID = '"&A4&"'" -> UPDATE [MAP].[T_TRANS_COST_CODE] SET NEW_COST_CODE_ID = '01-0000', NEW_ITEM_ID = ' ' WHERE LEGACY_COST_CODE_ID = '01-0000' AND DATA_FOLDER_ID = 'sampl' | G4: =IF(B4<>D4,"Changed","-") -> - | H4: =IF(B4="","Hide","-") -> -
A5: sampl | B5: 01-1005 | C5: Precon Project Executive | D5: 01-1005 | E5: Contract Item | F5: ="UPDATE "&F$3&" SET NEW_COST_CODE_ID = '"&D5&"', NEW_ITEM_ID = '"&E5&"' WHERE LEGACY_COST_CODE_ID = '"&B5&"' AND DATA_FOLDER_ID = '"&A5&"'" -> UPDATE [MAP].[T_TRANS_COST_CODE] SET NEW_COST_CODE_ID = '01-1005', NEW_ITEM_ID = 'Contract Item' WHERE LEGACY_COST_CODE_ID = '01-1005' AND DATA_FOLDER_ID = 'sampl' | G5: =IF(B5<>D5,"Changed","-") -> - | H5: =IF(B5="","Hide","-") -> -
A6: sampl | B6: 01-1008 | C6: Precon Senior Project Manager | D6: 01-1008 | E6: Contract Item | F6: ="UPDATE "&F$3&" SET NEW_COST_CODE_ID = '"&D6&"', NEW_ITEM_ID = '"&E6&"' WHERE LEGACY_COST_CODE_ID = '"&B6&"' AND DATA_FOLDER_ID = '"&A6&"'" -> UPDATE [MAP].[T_TRANS_COST_CODE] SET NEW_COST_CODE_ID = '01-1008', NEW_ITEM_ID = 'Contract Item' WHERE LEGACY_COST_CODE_ID = '01-1008' AND DATA_FOLDER_ID = 'sampl' | G6: =IF(B6<>D6,"Changed","-") -> - | H6: =IF(B6="","Hide","-") -> -
A7: sampl | B7: 01-1010 | C7: Precon Project Manager | D7: 01-1010 | E7: Contract Item | F7: ="UPDATE "&F$3&" SET NEW_COST_CODE_ID = '"&D7&"', NEW_ITEM_ID = '"&E7&"' WHERE LEGACY_COST_CODE_ID = '"&B7&"' AND DATA_FOLDER_ID = '"&A7&"'" -> UPDATE [MAP].[T_TRANS_COST_CODE] SET NEW_COST_CODE_ID = '01-1010', NEW_ITEM_ID = 'Contract Item' WHERE LEGACY_COST_CODE_ID = '01-1010' AND DATA_FOLDER_ID = 'sampl' | G7: =IF(B7<>D7,"Changed","-") -> - | H7: =IF(B7="","Hide","-") -> -
A8: sampl | B8: 01-1012 | C8: Precon Project Manager Assist | D8: 01-1212 | E8: Contract Item | F8: ="UPDATE "&F$3&" SET NEW_COST_CODE_ID = '"&D8&"', NEW_ITEM_ID = '"&E8&"' WHERE LEGACY_COST_CODE_ID = '"&B8&"' AND DATA_FOLDER_ID = '"&A8&"'" -> UPDATE [MAP].[T_TRANS_COST_CODE] SET NEW_COST_CODE_ID = '01-1212', NEW_ITEM_ID = 'Contract Item' WHERE LEGACY_COST_CODE_ID = '01-1012' AND DATA_FOLDER_ID = 'sampl' | G8: =IF(B8<>D8,"Changed","-") -> Changed | H8: =IF(B8="","Hide","-") -> -
A9: sampl | B9: 01-1015 | C9: Precon Construction Manager | D9: 01-1015 | E9: Contract Item | F9: ="UPDATE "&F$3&" SET NEW_COST_CODE_ID = '"&D9&"', NEW_ITEM_ID = '"&E9&"' WHERE LEGACY_COST_CODE_ID = '"&B9&"' AND DATA_FOLDER_ID = '"&A9&"'" -> UPDATE [MAP].[T_TRANS_COST_CODE] SET NEW_COST_CODE_ID = '01-1015', NEW_ITEM_ID = 'Contract Item' WHERE LEGACY_COST_CODE_ID = '01-1015' AND DATA_FOLDER_ID = 'sampl' | G9: =IF(B9<>D9,"Changed","-") -> - | H9: =IF(B9="","Hide","-") -> -
A10: sampl | B10: 01-1016 | C10: Precon Construction Mgr Senior | D10: 01-1016 | E10: Contract Item | F10: ="UPDATE "&F$3&" SET NEW_COST_CODE_ID = '"&D10&"', NEW_ITEM_ID = '"&E10&"' WHERE LEGACY_COST_CODE_ID = '"&B10&"' AND DATA_FOLDER_ID = '"&A10&"'" -> UPDATE [MAP].[T_TRANS_COST_CODE] SET NEW_COST_CODE_ID = '01-1016', NEW_ITEM_ID = 'Contract Item' WHERE LEGACY_COST_CODE_ID = '01-1016' AND DATA_FOLDER_ID = 'sampl' | G10: =IF(B10<>D10,"Changed","-") -> - | H10: =IF(B10="","Hide","-") -> -
A11: sampl | B11: 01-1020 | C11: Precon Superintendent | D11: 01-1020 | E11: Contract Item | F11: ="UPDATE "&F$3&" SET NEW_COST_CODE_ID = '"&D11&"', NEW_ITEM_ID = '"&E11&"' WHERE LEGACY_COST_CODE_ID = '"&B11&"' AND DATA_FOLDER_ID = '"&A11&"'" -> UPDATE [MAP].[T_TRANS_COST_CODE] SET NEW_COST_CODE_ID = '01-1020', NEW_ITEM_ID = 'Contract Item' WHERE LEGACY_COST_CODE_ID = '01-1020' AND DATA_FOLDER_ID = 'sampl' | G11: =IF(B11<>D11,"Changed","-") -> - | H11: =IF(B11="","Hide","-") -> -
A12: sampl | B12: 01-1025 | C12: Precon Business Development | D12: 01-1025 | E12: Contract Item | F12: ="UPDATE "&F$3&" SET NEW_COST_CODE_ID = '"&D12&"', NEW_ITEM_ID = '"&E12&"' WHERE LEGACY_COST_CODE_ID = '"&B12&"' AND DATA_FOLDER_ID = '"&A12&"'" -> UPDATE [MAP].[T_TRANS_COST_CODE] SET NEW_COST_CODE_ID = '01-1025', NEW_ITEM_ID = 'Contract Item' WHERE LEGACY_COST_CODE_ID = '01-1025' AND DATA_FOLDER_ID = 'sampl' | G12: =IF(B12<>D12,"Changed","-") -> - | H12: =IF(B12="","Hide","-") -> -
A13: sampl | B13: 01-1030 | C13: Precon Safety Coordinator | D13: 01-1030 | E13: Contract Item | F13: ="UPDATE "&F$3&" SET NEW_COST_CODE_ID = '"&D13&"', NEW_ITEM_ID = '"&E13&"' WHERE LEGACY_COST_CODE_ID = '"&B13&"' AND DATA_FOLDER_ID = '"&A13&"'" -> UPDATE [MAP].[T_TRANS_COST_CODE] SET NEW_COST_CODE_ID = '01-1030', NEW_ITEM_ID = 'Contract Item' WHERE LEGACY_COST_CODE_ID = '01-1030' AND DATA_FOLDER_ID = 'sampl' | G13: =IF(B13<>D13,"Changed","-") -> - | H13: =IF(B13="","Hide","-") -> -
A14: sampl | B14: 01-1040 | C14: Precon Project Engineer | D14: 01-1040 | E14: Contract Item | F14: ="UPDATE "&F$3&" SET NEW_COST_CODE_ID = '"&D14&"', NEW_ITEM_ID = '"&E14&"' WHERE LEGACY_COST_CODE_ID = '"&B14&"' AND DATA_FOLDER_ID = '"&A14&"'" -> UPDATE [MAP].[T_TRANS_COST_CODE] SET NEW_COST_CODE_ID = '01-1040', NEW_ITEM_ID = 'Contract Item' WHERE LEGACY_COST_CODE_ID = '01-1040' AND DATA_FOLDER_ID = 'sampl' | G14: =IF(B14<>D14,"Changed","-") -> - | H14: =IF(B14="","Hide","-") -> -
A15: sampl | B15: 01-1045 | C15: Precon Quality Control Manager | D15: 01-1045 | E15: Contract Item | F15: ="UPDATE "&F$3&" SET NEW_COST_CODE_ID = '"&D15&"', NEW_ITEM_ID = '"&E15&"' WHERE LEGACY_COST_CODE_ID = '"&B15&"' AND DATA_FOLDER_ID = '"&A15&"'" -> UPDATE [MAP].[T_TRANS_COST_CODE] SET NEW_COST_CODE_ID = '01-1045', NEW_ITEM_ID = 'Contract Item' WHERE LEGACY_COST_CODE_ID = '01-1045' AND DATA_FOLDER_ID = 'sampl' | G15: =IF(B15<>D15,"Changed","-") -> - | H15: =IF(B15="","Hide","-") -> -
A16: sampl | B16: 01-1050 | C16: Precon Project Assistant | D16: 01-1050 | E16: Contract Item | F16: ="UPDATE "&F$3&" SET NEW_COST_CODE_ID = '"&D16&"', NEW_ITEM_ID = '"&E16&"' WHERE LEGACY_COST_CODE_ID = '"&B16&"' AND DATA_FOLDER_ID = '"&A16&"'" -> UPDATE [MAP].[T_TRANS_COST_CODE] SET NEW_COST_CODE_ID = '01-1050', NEW_ITEM_ID = 'Contract Item' WHERE LEGACY_COST_CODE_ID = '01-1050' AND DATA_FOLDER_ID = 'sampl' | G16: =IF(B16<>D16,"Changed","-") -> - | H16: =IF(B16="","Hide","-") -> -
... A39: sampl | B39: 01-1210 | C39: Layout | D39: 01-1215 | E39: Contract Item | F39: ="UPDATE "&F$3&" SET NEW_COST_CODE_ID = '"&D39&"', NEW_ITEM_ID = '"&E39&"' WHERE LEGACY_COST_CODE_ID = '"&B39&"' AND DATA_FOLDER_ID = '"&A39&"'" -> UPDATE [MAP].[T_TRANS_COST_CODE] SET NEW_COST_CODE_ID = '01-1215', NEW_ITEM_ID = 'Contract Item' WHERE LEGACY_COST_CODE_ID = '01-1210' AND DATA_FOLDER_ID = 'sampl' | G39: =IF(B39<>D39,"Changed","-") -> Changed | H39: =IF(B39="","Hide","-") -> -
A40: sampl | B40: 01-1215 | F40: ="UPDATE "&F$3&" SET NEW_COST_CODE_ID = '"&D40&"', NEW_ITEM_ID = '"&E40&"' WHERE LEGACY_COST_CODE_ID = '"&B40&"' AND DATA_FOLDER_ID = '"&A40&"'" -> UPDATE [MAP].[T_TRANS_COST_CODE] SET NEW_COST_CODE_ID = '', NEW_ITEM_ID = '' WHERE LEGACY_COST_CODE_ID = '01-1215' AND DATA_FOLDER_ID = 'sampl' | G40: =IF(B40<>D40,"Changed","-") -> Changed | H40: =IF(B40="","Hide","-") -> -
A41: sampl | B41: 01-1220 | C41: Safety Requirements | D41: 01-1220 | E41: Contract Item | F41: ="UPDATE "&F$3&" SET NEW_COST_CODE_ID = '"&D41&"', NEW_ITEM_ID = '"&E41&"' WHERE LEGACY_COST_CODE_ID = '"&B41&"' AND DATA_FOLDER_ID = '"&A41&"'" -> UPDATE [MAP].[T_TRANS_COST_CODE] SET NEW_COST_CODE_ID = '01-1220', NEW_ITEM_ID = 'Contract Item' WHERE LEGACY_COST_CODE_ID = '01-1220' AND DATA_FOLDER_ID = 'sampl' | G41: =IF(B41<>D41,"Changed","-") -> - | H41: =IF(B41="","Hide","-") -> -
A42: sampl | B42: 01-1225 | C42: Field Office Trailer | D42: 01-1225 | E42: Contract Item | F42: ="UPDATE "&F$3&" SET NEW_COST_CODE_ID = '"&D42&"', NEW_ITEM_ID = '"&E42&"' WHERE LEGACY_COST_CODE_ID = '"&B42&"' AND DATA_FOLDER_ID = '"&A42&"'" -> UPDATE [MAP].[T_TRANS_COST_CODE] SET NEW_COST_CODE_ID = '01-1225', NEW_ITEM_ID = 'Contract Item' WHERE LEGACY_COST_CODE_ID = '01-1225' AND DATA_FOLDER_ID = 'sampl' | G42: =IF(B42<>D42,"Changed","-") -> - | H42: =IF(B42="","Hide","-") -> -
A43: sampl | B43: 01-1240 | C43: Storage Trailer | D43: 01-1240 | E43: Contract Item | F43: ="UPDATE "&F$3&" SET NEW_COST_CODE_ID = '"&D43&"', NEW_ITEM_ID = '"&E43&"' WHERE LEGACY_COST_CODE_ID = '"&B43&"' AND DATA_FOLDER_ID = '"&A43&"'" -> UPDATE [MAP].[T_TRANS_COST_CODE] SET NEW_COST_CODE_ID = '01-1240', NEW_ITEM_ID = 'Contract Item' WHERE LEGACY_COST_CODE_ID = '01-1240' AND DATA_FOLDER_ID = 'sampl' | G43: =IF(B43<>D43,"Changed","-") -> - | H43: =IF(B43="","Hide","-") -> -
A44: sampl | B44: 01-1245 | C44: Job Security | D44: 01-1245 | E44: Contract Item | F44: ="UPDATE "&F$3&" SET NEW_COST_CODE_ID = '"&D44&"', NEW_ITEM_ID = '"&E44&"' WHERE LEGACY_COST_CODE_ID = '"&B44&"' AND DATA_FOLDER_ID = '"&A44&"'" -> UPDATE [MAP].[T_TRANS_COST_CODE] SET NEW_COST_CODE_ID = '01-1245', NEW_ITEM_ID = 'Contract Item' WHERE LEGACY_COST_CODE_ID = '01-1245' AND DATA_FOLDER_ID = 'sampl' | G44: =IF(B44<>D44,"Changed","-") -> - | H44: =IF(B44="","Hide","-") -> -
A45: sampl | B45: 01-1250 | C45: Photographs | D45: 01-1250 | E45: Contract Item | F45: ="UPDATE "&F$3&" SET NEW_COST_CODE_ID = '"&D45&"', NEW_ITEM_ID = '"&E45&"' WHERE LEGACY_COST_CODE_ID = '"&B45&"' AND DATA_FOLDER_ID = '"&A45&"'" -> UPDATE [MAP].[T_TRANS_COST_CODE] SET NEW_COST_CODE_ID = '01-1250', NEW_ITEM_ID = 'Contract Item' WHERE LEGACY_COST_CODE_ID = '01-1250' AND DATA_FOLDER_ID = 'sampl' | G45: =IF(B45<>D45,"Changed","-") -> - | H45: =IF(B45="","Hide","-") -> -
A46: sampl | B46: 01-1255 | C46: Shipping | D46: 01-1255 | E46: Contract Item | F46: ="UPDATE "&F$3&" SET NEW_COST_CODE_ID = '"&D46&"', NEW_ITEM_ID = '"&E46&"' WHERE LEGACY_COST_CODE_ID = '"&B46&"' AND DATA_FOLDER_ID = '"&A46&"'" -> UPDATE [MAP].[T_TRANS_COST_CODE] SET NEW_COST_CODE_ID = '01-1255', NEW_ITEM_ID = 'Contract Item' WHERE LEGACY_COST_CODE_ID = '01-1255' AND DATA_FOLDER_ID = 'sampl' | G46: =IF(B46<>D46,"Changed","-") -> - | H46: =IF(B46="","Hide","-") -> -
A47: sampl | B47: 01-1260 | C47: Drawings Reproduction | D47: 01-1260 | E47: Contract Item | F47: ="UPDATE "&F$3&" SET NEW_COST_CODE_ID = '"&D47&"', NEW_ITEM_ID = '"&E47&"' WHERE LEGACY_COST_CODE_ID = '"&B47&"' AND DATA_FOLDER_ID = '"&A47&"'" -> UPDATE [MAP].[T_TRANS_COST_CODE] SET NEW_COST_CODE_ID = '01-1260', NEW_ITEM_ID = 'Contract Item' WHERE LEGACY_COST_CODE_ID = '01-1260' AND DATA_FOLDER_ID = 'sampl' | G47: =IF(B47<>D47,"Changed","-") -> - | H47: =IF(B47="","Hide","-") -> -
A48: sampl | B48: 01-1265 | C48: Small Tools | D48: 01-1265 | E48: Contract Item | F48: ="UPDATE "&F$3&" SET NEW_COST_CODE_ID = '"&D48&"', NEW_ITEM_ID = '"&E48&"' WHERE LEGACY_COST_CODE_ID = '"&B48&"' AND DATA_FOLDER_ID = '"&A48&"'" -> UPDATE [MAP].[T_TRANS_COST_CODE] SET NEW_COST_CODE_ID = '01-1265', NEW_ITEM_ID = 'Contract Item' WHERE LEGACY_COST_CODE_ID = '01-1265' AND DATA_FOLDER_ID = 'sampl' | G48: =IF(B48<>D48,"Changed","-") -> - | H48: =IF(B48="","Hide","-") -> -
A49: sampl | B49: 01-1270 | C49: Current Clean-up | D49: 01-1270 | E49: Contract Item | F49: ="UPDATE "&F$3&" SET NEW_COST_CODE_ID = '"&D49&"', NEW_ITEM_ID = '"&E49&"' WHERE LEGACY_COST_CODE_ID = '"&B49&"' AND DATA_FOLDER_ID = '"&A49&"'" -> UPDATE [MAP].[T_TRANS_COST_CODE] SET NEW_COST_CODE_ID = '01-1270', NEW_ITEM_ID = 'Contract Item' WHERE LEGACY_COST_CODE_ID = '01-1270' AND DATA_FOLDER_ID = 'sampl' | G49: =IF(B49<>D49,"Changed","-") -> - | H49: =IF(B49="","Hide","-") -> -
A50: sampl | B50: 01-1275 | C50: Dumpsters | D50: 01-1275 | E50: Contract Item | F50: ="UPDATE "&F$3&" SET NEW_COST_CODE_ID = '"&D50&"', NEW_ITEM_ID = '"&E50&"' WHERE LEGACY_COST_CODE_ID = '"&B50&"' AND DATA_FOLDER_ID = '"&A50&"'" -> UPDATE [MAP].[T_TRANS_COST_CODE] SET NEW_COST_CODE_ID = '01-1275', NEW_ITEM_ID = 'Contract Item' WHERE LEGACY_COST_CODE_ID = '01-1275' AND DATA_FOLDER_ID = 'sampl' | G50: =IF(B50<>D50,"Changed","-") -> - | H50: =IF(B50="","Hide","-") -> -
A51: sampl | B51: 01-1300 | C51: Legal Fees | D51: 01-1300 | E51: Contract Item | F51: ="UPDATE "&F$3&" SET NEW_COST_CODE_ID = '"&D51&"', NEW_ITEM_ID = '"&E51&"' WHERE LEGACY_COST_CODE_ID = '"&B51&"' AND DATA_FOLDER_ID = '"&A51&"'" -> UPDATE [MAP].[T_TRANS_COST_CODE] SET NEW_COST_CODE_ID = '01-1300', NEW_ITEM_ID = 'Contract Item' WHERE LEGACY_COST_CODE_ID = '01-1300' AND DATA_FOLDER_ID = 'sampl' | G51: =IF(B51<>D51,"Changed","-") -> - | H51: =IF(B51="","Hide","-") -> -
A52: sampl | B52: 01-1305 | C52: Architectural Engineering Serv | D52: 01-1305 | E52: Contract Item | F52: ="UPDATE "&F$3&" SET NEW_COST_CODE_ID = '"&D52&"', NEW_ITEM_ID = '"&E52&"' WHERE LEGACY_COST_CODE_ID = '"&B52&"' AND DATA_FOLDER_ID = '"&A52&"'" -> UPDATE [MAP].[T_TRANS_COST_CODE] SET NEW_COST_CODE_ID = '01-1305', NEW_ITEM_ID = 'Contract Item' WHERE LEGACY_COST_CODE_ID = '01-1305' AND DATA_FOLDER_ID = 'sampl' | G52: =IF(B52<>D52,"Changed","-") -> - | H52: =IF(B52="","Hide","-") -> -
... A81: sampl | B81: 01-5123 | C81: Temp Heat, Cooling & Vent | D81: 01-5123 | E81: Contract Item | F81: ="UPDATE "&F$3&" SET NEW_COST_CODE_ID = '"&D81&"', NEW_ITEM_ID = '"&E81&"' WHERE LEGACY_COST_CODE_ID = '"&B81&"' AND DATA_FOLDER_ID = '"&A81&"'" -> UPDATE [MAP].[T_TRANS_COST_CODE] SET NEW_COST_CODE_ID = '01-5123', NEW_ITEM_ID = 'Contract Item' WHERE LEGACY_COST_CODE_ID = '01-5123' AND DATA_FOLDER_ID = 'sampl' | G81: =IF(B81<>D81,"Changed","-") -> - | H81: =IF(B81="","Hide","-") -> -
A82: sampl | B82: 02-0000 | C82: EXISTING CONDITIONS | D82: 02-0000 | F82: ="UPDATE "&F$3&" SET NEW_COST_CODE_ID = '"&D82&"', NEW_ITEM_ID = '"&E82&"' WHERE LEGACY_COST_CODE_ID = '"&B82&"' AND DATA_FOLDER_ID = '"&A82&"'" -> UPDATE [MAP].[T_TRANS_COST_CODE] SET NEW_COST_CODE_ID = '02-0000', NEW_ITEM_ID = ' ' WHERE LEGACY_COST_CODE_ID = '02-0000' AND DATA_FOLDER_ID = 'sampl' | G82: =IF(B82<>D82,"Changed","-") -> - | H82: =IF(B82="","Hide","-") -> -
A83: sampl | B83: 02-3000 | C83: Subsurface Investigation | D83: 02-3000 | E83: Contract Item | F83: ="UPDATE "&F$3&" SET NEW_COST_CODE_ID = '"&D83&"', NEW_ITEM_ID = '"&E83&"' WHERE LEGACY_COST_CODE_ID = '"&B83&"' AND DATA_FOLDER_ID = '"&A83&"'" -> UPDATE [MAP].[T_TRANS_COST_CODE] SET NEW_COST_CODE_ID = '02-3000', NEW_ITEM_ID = 'Contract Item' WHERE LEGACY_COST_CODE_ID = '02-3000' AND DATA_FOLDER_ID = 'sampl' | G83: =IF(B83<>D83,"Changed","-") -> - | H83: =IF(B83="","Hide","-") -> -
A84: sampl | B84: 02-4113 | C84: Selective Site Demolition | D84: 02-4113 | E84: Contract Item | F84: ="UPDATE "&F$3&" SET NEW_COST_CODE_ID = '"&D84&"', NEW_ITEM_ID = '"&E84&"' WHERE LEGACY_COST_CODE_ID = '"&B84&"' AND DATA_FOLDER_ID = '"&A84&"'" -> UPDATE [MAP].[T_TRANS_COST_CODE] SET NEW_COST_CODE_ID = '02-4113', NEW_ITEM_ID = 'Contract Item' WHERE LEGACY_COST_CODE_ID = '02-4113' AND DATA_FOLDER_ID = 'sampl' | G84: =IF(B84<>D84,"Changed","-") -> - | H84: =IF(B84="","Hide","-") -> -
A85: sampl | B85: 02-4116 | C85: Structure Demolition | D85: 02-4116 | E85: Contract Item | F85: ="UPDATE "&F$3&" SET NEW_COST_CODE_ID = '"&D85&"', NEW_ITEM_ID = '"&E85&"' WHERE LEGACY_COST_CODE_ID = '"&B85&"' AND DATA_FOLDER_ID = '"&A85&"'" -> UPDATE [MAP].[T_TRANS_COST_CODE] SET NEW_COST_CODE_ID = '02-4116', NEW_ITEM_ID = 'Contract Item' WHERE LEGACY_COST_CODE_ID = '02-4116' AND DATA_FOLDER_ID = 'sampl' | G85: =IF(B85<>D85,"Changed","-") -> - | H85: =IF(B85="","Hide","-") -> -
A86: sampl | B86: 02-4119 | C86: Selective Demolition | D86: 02-4119 | E86: Contract Item | F86: ="UPDATE "&F$3&" SET NEW_COST_CODE_ID = '"&D86&"', NEW_ITEM_ID = '"&E86&"' WHERE LEGACY_COST_CODE_ID = '"&B86&"' AND DATA_FOLDER_ID = '"&A86&"'" -> UPDATE [MAP].[T_TRANS_COST_CODE] SET NEW_COST_CODE_ID = '02-4119', NEW_ITEM_ID = 'Contract Item' WHERE LEGACY_COST_CODE_ID = '02-4119' AND DATA_FOLDER_ID = 'sampl' | G86: =IF(B86<>D86,"Changed","-") -> - | H86: =IF(B86="","Hide","-") -> -
A87: sampl | B87: 02-4901 | C87: Flatwork Concrete Removal | D87: 02-4901 | E87: Contract Item | F87: ="UPDATE "&F$3&" SET NEW_COST_CODE_ID = '"&D87&"', NEW_ITEM_ID = '"&E87&"' WHERE LEGACY_COST_CODE_ID = '"&B87&"' AND DATA_FOLDER_ID = '"&A87&"'" -> UPDATE [MAP].[T_TRANS_COST_CODE] SET NEW_COST_CODE_ID = '02-4901', NEW_ITEM_ID = 'Contract Item' WHERE LEGACY_COST_CODE_ID = '02-4901' AND DATA_FOLDER_ID = 'sampl' | G87: =IF(B87<>D87,"Changed","-") -> - | H87: =IF(B87="","Hide","-") -> -
A88: sampl | B88: 02-4902 | C88: Structural Concrete Removal | D88: 02-4902 | E88: Contract Item | F88: ="UPDATE "&F$3&" SET NEW_COST_CODE_ID = '"&D88&"', NEW_ITEM_ID = '"&E88&"' WHERE LEGACY_COST_CODE_ID = '"&B88&"' AND DATA_FOLDER_ID = '"&A88&"'" -> UPDATE [MAP].[T_TRANS_COST_CODE] SET NEW_COST_CODE_ID = '02-4902', NEW_ITEM_ID = 'Contract Item' WHERE LEGACY_COST_CODE_ID = '02-4902' AND DATA_FOLDER_ID = 'sampl' | G88: =IF(B88<>D88,"Changed","-") -> - | H88: =IF(B88="","Hide","-") -> -
A89: sampl | B89: 02-4903 | C89: Concrete Demolition | D89: 02-4903 | E89: Contract Item | F89: ="UPDATE "&F$3&" SET NEW_COST_CODE_ID = '"&D89&"', NEW_ITEM_ID = '"&E89&"' WHERE LEGACY_COST_CODE_ID = '"&B89&"' AND DATA_FOLDER_ID = '"&A89&"'" -> UPDATE [MAP].[T_TRANS_COST_CODE] SET NEW_COST_CODE_ID = '02-4903', NEW_ITEM_ID = 'Contract Item' WHERE LEGACY_COST_CODE_ID = '02-4903' AND DATA_FOLDER_ID = 'sampl' | G89: =IF(B89<>D89,"Changed","-") -> - | H89: =IF(B89="","Hide","-") -> -
A90: sampl | B90: 02-4904 | C90: Masonry Demolition | D90: 02-4904 | E90: Contract Item | F90: ="UPDATE "&F$3&" SET NEW_COST_CODE_ID = '"&D90&"', NEW_ITEM_ID = '"&E90&"' WHERE LEGACY_COST_CODE_ID = '"&B90&"' AND DATA_FOLDER_ID = '"&A90&"'" -> UPDATE [MAP].[T_TRANS_COST_CODE] SET NEW_COST_CODE_ID = '02-4904', NEW_ITEM_ID = 'Contract Item' WHERE LEGACY_COST_CODE_ID = '02-4904' AND DATA_FOLDER_ID = 'sampl' | G90: =IF(B90<>D90,"Changed","-") -> - | H90: =IF(B90="","Hide","-") -> -
A91: sampl | B91: 02-4905 | C91: Steel Demolition | D91: 02-4905 | E91: Contract Item | F91: ="UPDATE "&F$3&" SET NEW_COST_CODE_ID = '"&D91&"', NEW_ITEM_ID = '"&E91&"' WHERE LEGACY_COST_CODE_ID = '"&B91&"' AND DATA_FOLDER_ID = '"&A91&"'" -> UPDATE [MAP].[T_TRANS_COST_CODE] SET NEW_COST_CODE_ID = '02-4905', NEW_ITEM_ID = 'Contract Item' WHERE LEGACY_COST_CODE_ID = '02-4905' AND DATA_FOLDER_ID = 'sampl' | G91: =IF(B91<>D91,"Changed","-") -> - | H91: =IF(B91="","Hide","-") -> -
A92: sampl | B92: 02-5000 | C92: Soil Remediation | D92: 02-5000 | E92: Contract Item | F92: ="UPDATE "&F$3&" SET NEW_COST_CODE_ID = '"&D92&"', NEW_ITEM_ID = '"&E92&"' WHERE LEGACY_COST_CODE_ID = '"&B92&"' AND DATA_FOLDER_ID = '"&A92&"'" -> UPDATE [MAP].[T_TRANS_COST_CODE] SET NEW_COST_CODE_ID = '02-5000', NEW_ITEM_ID = 'Contract Item' WHERE LEGACY_COST_CODE_ID = '02-5000' AND DATA_FOLDER_ID = 'sampl' | G92: =IF(B92<>D92,"Changed","-") -> - | H92: =IF(B92="","Hide","-") -> -
A93: sampl | B93: 02-8000 | C93: Hazardous Material Remediation | D93: 02-8000 | E93: Contract Item | F93: ="UPDATE "&F$3&" SET NEW_COST_CODE_ID = '"&D93&"', NEW_ITEM_ID = '"&E93&"' WHERE LEGACY_COST_CODE_ID = '"&B93&"' AND DATA_FOLDER_ID = '"&A93&"'" -> UPDATE [MAP].[T_TRANS_COST_CODE] SET NEW_COST_CODE_ID = '02-8000', NEW_ITEM_ID = 'Contract Item' WHERE LEGACY_COST_CODE_ID = '02-8000' AND DATA_FOLDER_ID = 'sampl' | G93: =IF(B93<>D93,"Changed","-") -> - | H93: =IF(B93="","Hide","-") -> -
A94: sampl | B94: 03-0000 | C94: CONCRETE | D94: 03-0000 | F94: ="UPDATE "&F$3&" SET NEW_COST_CODE_ID = '"&D94&"', NEW_ITEM_ID = '"&E94&"' WHERE LEGACY_COST_CODE_ID = '"&B94&"' AND DATA_FOLDER_ID = '"&A94&"'" -> UPDATE [MAP].[T_TRANS_COST_CODE] SET NEW_COST_CODE_ID = '03-0000', NEW_ITEM_ID = ' ' WHERE LEGACY_COST_CODE_ID = '03-0000' AND DATA_FOLDER_ID = 'sampl' | G94: =IF(B94<>D94,"Changed","-") -> - | H94: =IF(B94="","Hide","-") -> -
A95: sampl | B95: 03-0130 | C95: Concrete Restoration | D95: 03-0130 | E95: Contract Item | F95: ="UPDATE "&F$3&" SET NEW_COST_CODE_ID = '"&D95&"', NEW_ITEM_ID = '"&E95&"' WHERE LEGACY_COST_CODE_ID = '"&B95&"' AND DATA_FOLDER_ID = '"&A95&"'" -> UPDATE [MAP].[T_TRANS_COST_CODE] SET NEW_COST_CODE_ID = '03-0130', NEW_ITEM_ID = 'Contract Item' WHERE LEGACY_COST_CODE_ID = '03-0130' AND DATA_FOLDER_ID = 'sampl' | G95: =IF(B95<>D95,"Changed","-") -> - | H95: =IF(B95="","Hide","-") -> -
A96: sampl | B96: 03-0131 | C96: Top Side Repairs | D96: 03-0131 | E96: Contract Item | F96: ="UPDATE "&F$3&" SET NEW_COST_CODE_ID = '"&D96&"', NEW_ITEM_ID = '"&E96&"' WHERE LEGACY_COST_CODE_ID = '"&B96&"' AND DATA_FOLDER_ID = '"&A96&"'" -> UPDATE [MAP].[T_TRANS_COST_CODE] SET NEW_COST_CODE_ID = '03-0131', NEW_ITEM_ID = 'Contract Item' WHERE LEGACY_COST_CODE_ID = '03-0131' AND DATA_FOLDER_ID = 'sampl' | G96: =IF(B96<>D96,"Changed","-") -> - | H96: =IF(B96="","Hide","-") -> -
A97: sampl | B97: 03-0132 | C97: Bottom Side Repairs | D97: 03-0132 | E97: Contract Item | F97: ="UPDATE "&F$3&" SET NEW_COST_CODE_ID = '"&D97&"', NEW_ITEM_ID = '"&E97&"' WHERE LEGACY_COST_CODE_ID = '"&B97&"' AND DATA_FOLDER_ID = '"&A97&"'" -> UPDATE [MAP].[T_TRANS_COST_CODE] SET NEW_COST_CODE_ID = '03-0132', NEW_ITEM_ID = 'Contract Item' WHERE LEGACY_COST_CODE_ID = '03-0132' AND DATA_FOLDER_ID = 'sampl' | G97: =IF(B97<>D97,"Changed","-") -> - | H97: =IF(B97="","Hide","-") -> -
A98: sampl | B98: 03-0133 | C98: Full Depth Repairs | D98: 03-0133 | E98: Contract Item | F98: ="UPDATE "&F$3&" SET NEW_COST_CODE_ID = '"&D98&"', NEW_ITEM_ID = '"&E98&"' WHERE LEGACY_COST_CODE_ID = '"&B98&"' AND DATA_FOLDER_ID = '"&A98&"'" -> UPDATE [MAP].[T_TRANS_COST_CODE] SET NEW_COST_CODE_ID = '03-0133', NEW_ITEM_ID = 'Contract Item' WHERE LEGACY_COST_CODE_ID = '03-0133' AND DATA_FOLDER_ID = 'sampl' | G98: =IF(B98<>D98,"Changed","-") -> - | H98: =IF(B98="","Hide","-") -> -
A99: sampl | B99: 03-0134 | C99: Wall Repairs | D99: 03-0134 | E99: Contract Item | F99: ="UPDATE "&F$3&" SET NEW_COST_CODE_ID = '"&D99&"', NEW_ITEM_ID = '"&E99&"' WHERE LEGACY_COST_CODE_ID = '"&B99&"' AND DATA_FOLDER_ID = '"&A99&"'" -> UPDATE [MAP].[T_TRANS_COST_CODE] SET NEW_COST_CODE_ID = '03-0134', NEW_ITEM_ID = 'Contract Item' WHERE LEGACY_COST_CODE_ID = '03-0134' AND DATA_FOLDER_ID = 'sampl' | G99: =IF(B99<>D99,"Changed","-") -> - | H99: =IF(B99="","Hide","-") -> -
A100: sampl | B100: 03-0135 | C100: Joint Repairs | D100: 03-0135 | E100: Contract Item | F100: ="UPDATE "&F$3&" SET NEW_COST_CODE_ID = '"&D100&"', NEW_ITEM_ID = '"&E100&"' WHERE LEGACY_COST_CODE_ID = '"&B100&"' AND DATA_FOLDER_ID = '"&A100&"'" -> UPDATE [MAP].[T_TRANS_COST_CODE] SET NEW_COST_CODE_ID = '03-0135', NEW_ITEM_ID = 'Contract Item' WHERE LEGACY_COST_CODE_ID = '03-0135' AND DATA_FOLDER_ID = 'sampl' | G100: =IF(B100<>D100,"Changed","-") -> - | H100: =IF(B100="","Hide","-") -> -
A101: sampl | B101: 03-0136 | C101: Crack Repairs | D101: 03-0136 | E101: Contract Item | F101: ="UPDATE "&F$3&" SET NEW_COST_CODE_ID = '"&D101&"', NEW_ITEM_ID = '"&E101&"' WHERE LEGACY_COST_CODE_ID = '"&B101&"' AND DATA_FOLDER_ID = '"&A101&"'" -> UPDATE [MAP].[T_TRANS_COST_CODE] SET NEW_COST_CODE_ID = '03-0136', NEW_ITEM_ID = 'Contract Item' WHERE LEGACY_COST_CODE_ID = '03-0136' AND DATA_FOLDER_ID = 'sampl' | G101: =IF(B101<>D101,"Changed","-") -> - | H101: =IF(B101="","Hide","-") -> -
A102: sampl | B102: 03-1519 | C102: Cast-In Concrete Anchors | D102: 03-1519 | E102: Contract Item | F102: ="UPDATE "&F$3&" SET NEW_COST_CODE_ID = '"&D102&"', NEW_ITEM_ID = '"&E102&"' WHERE LEGACY_COST_CODE_ID = '"&B102&"' AND DATA_FOLDER_ID = '"&A102&"'" -> UPDATE [MAP].[T_TRANS_COST_CODE] SET NEW_COST_CODE_ID = '03-1519', NEW_ITEM_ID = 'Contract Item' WHERE LEGACY_COST_CODE_ID = '03-1519' AND DATA_FOLDER_ID = 'sampl' | G102: =IF(B102<>D102,"Changed","-") -> - | H102: =IF(B102="","Hide","-") -> -
A103: sampl | B103: 03-1520 | C103: Drilled Dowels | D103: 03-1520 | E103: Contract Item | F103: ="UPDATE "&F$3&" SET NEW_COST_CODE_ID = '"&D103&"', NEW_ITEM_ID = '"&E103&"' WHERE LEGACY_COST_CODE_ID = '"&B103&"' AND DATA_FOLDER_ID = '"&A103&"'" -> UPDATE [MAP].[T_TRANS_COST_CODE] SET NEW_COST_CODE_ID = '03-1520', NEW_ITEM_ID = 'Contract Item' WHERE LEGACY_COST_CODE_ID = '03-1520' AND DATA_FOLDER_ID = 'sampl' | G103: =IF(B103<>D103,"Changed","-") -> - | H103: =IF(B103="","Hide","-") -> -
A104: sampl | B104: 03-2100 | C104: Reinforcement Bars | D104: 03-2100 | E104: Contract Item | F104: ="UPDATE "&F$3&" SET NEW_COST_CODE_ID = '"&D104&"', NEW_ITEM_ID = '"&E104&"' WHERE LEGACY_COST_CODE_ID = '"&B104&"' AND DATA_FOLDER_ID = '"&A104&"'" -> UPDATE [MAP].[T_TRANS_COST_CODE] SET NEW_COST_CODE_ID = '03-2100', NEW_ITEM_ID = 'Contract Item' WHERE LEGACY_COST_CODE_ID = '03-2100' AND DATA_FOLDER_ID = 'sampl' | G104: =IF(B104<>D104,"Changed","-") -> - | H104: =IF(B104="","Hide","-") -> -
A105: sampl | B105: 03-2200 | C105: Fabric & Grid Reinforcing | D105: 03-2200 | E105: Contract Item | F105: ="UPDATE "&F$3&" SET NEW_COST_CODE_ID = '"&D105&"', NEW_ITEM_ID = '"&E105&"' WHERE LEGACY_COST_CODE_ID = '"&B105&"' AND DATA_FOLDER_ID = '"&A105&"'" -> UPDATE [MAP].[T_TRANS_COST_CODE] SET NEW_COST_CODE_ID = '03-2200', NEW_ITEM_ID = 'Contract Item' WHERE LEGACY_COST_CODE_ID = '03-2200' AND DATA_FOLDER_ID = 'sampl' | G105: =IF(B105<>D105,"Changed","-") -> - | H105: =IF(B105="","Hide","-") -> -
A106: sampl | B106: 03-3010 | C106: Concrete, Strip Footings | D106: 03-3010 | E106: Contract Item | F106: ="UPDATE "&F$3&" SET NEW_COST_CODE_ID = '"&D106&"', NEW_ITEM_ID = '"&E106&"' WHERE LEGACY_COST_CODE_ID = '"&B106&"' AND DATA_FOLDER_ID = '"&A106&"'" -> UPDATE [MAP].[T_TRANS_COST_CODE] SET NEW_COST_CODE_ID = '03-3010', NEW_ITEM_ID = 'Contract Item' WHERE LEGACY_COST_CODE_ID = '03-3010' AND DATA_FOLDER_ID = 'sampl' | G106: =IF(B106<>D106,"Changed","-") -> - | H106: =IF(B106="","Hide","-") -> -
... A126: sampl | B126: 03-8200 | C126: Concrete Boring | D126: 03-8200 | E126: Contract Item | F126: ="UPDATE "&F$3&" SET NEW_COST_CODE_ID = '"&D126&"', NEW_ITEM_ID = '"&E126&"' WHERE LEGACY_COST_CODE_ID = '"&B126&"' AND DATA_FOLDER_ID = '"&A126&"'" -> UPDATE [MAP].[T_TRANS_COST_CODE] SET NEW_COST_CODE_ID = '03-8200', NEW_ITEM_ID = 'Contract Item' WHERE LEGACY_COST_CODE_ID = '03-8200' AND DATA_FOLDER_ID = 'sampl' | G126: =IF(B126<>D126,"Changed","-") -> - | H126: =IF(B126="","Hide","-") -> -
A127: sampl | B127: 04-0000 | C127: MASONRY | D127: 04-0000 | F127: ="UPDATE "&F$3&" SET NEW_COST_CODE_ID = '"&D127&"', NEW_ITEM_ID = '"&E127&"' WHERE LEGACY_COST_CODE_ID = '"&B127&"' AND DATA_FOLDER_ID = '"&A127&"'" -> UPDATE [MAP].[T_TRANS_COST_CODE] SET NEW_COST_CODE_ID = '04-0000', NEW_ITEM_ID = ' ' WHERE LEGACY_COST_CODE_ID = '04-0000' AND DATA_FOLDER_ID = 'sampl' | G127: =IF(B127<>D127,"Changed","-") -> - | H127: =IF(B127="","Hide","-") -> -
A128: sampl | B128: 04-0120 | C128: Masonry Restoration | D128: 04-0120 | E128: Contract Item | F128: ="UPDATE "&F$3&" SET NEW_COST_CODE_ID = '"&D128&"', NEW_ITEM_ID = '"&E128&"' WHERE LEGACY_COST_CODE_ID = '"&B128&"' AND DATA_FOLDER_ID = '"&A128&"'" -> UPDATE [MAP].[T_TRANS_COST_CODE] SET NEW_COST_CODE_ID = '04-0120', NEW_ITEM_ID = 'Contract Item' WHERE LEGACY_COST_CODE_ID = '04-0120' AND DATA_FOLDER_ID = 'sampl' | G128: =IF(B128<>D128,"Changed","-") -> - | H128: =IF(B128="","Hide","-") -> -
A129: sampl | B129: 04-2000 | C129: Masonry | D129: 04-2000 | E129: Contract Item | F129: ="UPDATE "&F$3&" SET NEW_COST_CODE_ID = '"&D129&"', NEW_ITEM_ID = '"&E129&"' WHERE LEGACY_COST_CODE_ID = '"&B129&"' AND DATA_FOLDER_ID = '"&A129&"'" -> UPDATE [MAP].[T_TRANS_COST_CODE] SET NEW_COST_CODE_ID = '04-2000', NEW_ITEM_ID = 'Contract Item' WHERE LEGACY_COST_CODE_ID = '04-2000' AND DATA_FOLDER_ID = 'sampl' | G129: =IF(B129<>D129,"Changed","-") -> - | H129: =IF(B129="","Hide","-") -> -
A130: sampl | B130: 05-0000 | C130: METALS | D130: 05-0000 | F130: ="UPDATE "&F$3&" SET NEW_COST_CODE_ID = '"&D130&"', NEW_ITEM_ID = '"&E130&"' WHERE LEGACY_COST_CODE_ID = '"&B130&"' AND DATA_FOLDER_ID = '"&A130&"'" -> UPDATE [MAP].[T_TRANS_COST_CODE] SET NEW_COST_CODE_ID = '05-0000', NEW_ITEM_ID = ' ' WHERE LEGACY_COST_CODE_ID = '05-0000' AND DATA_FOLDER_ID = 'sampl' | G130: =IF(B130<>D130,"Changed","-") -> - | H130: =IF(B130="","Hide","-") -> -
A131: sampl | B131: 05-1000 | C131: Structural Steel | D131: 05-1000 | E131: Contract Item | F131: ="UPDATE "&F$3&" SET NEW_COST_CODE_ID = '"&D131&"', NEW_ITEM_ID = '"&E131&"' WHERE LEGACY_COST_CODE_ID = '"&B131&"' AND DATA_FOLDER_ID = '"&A131&"'" -> UPDATE [MAP].[T_TRANS_COST_CODE] SET NEW_COST_CODE_ID = '05-1000', NEW_ITEM_ID = 'Contract Item' WHERE LEGACY_COST_CODE_ID = '05-1000' AND DATA_FOLDER_ID = 'sampl' | G131: =IF(B131<>D131,"Changed","-") -> - | H131: =IF(B131="","Hide","-") -> -
A132: sampl | B132: 05-4100 | C132: Metal Framing - Load Bear | D132: 05-4100 | E132: Contract Item | F132: ="UPDATE "&F$3&" SET NEW_COST_CODE_ID = '"&D132&"', NEW_ITEM_ID = '"&E132&"' WHERE LEGACY_COST_CODE_ID = '"&B132&"' AND DATA_FOLDER_ID = '"&A132&"'" -> UPDATE [MAP].[T_TRANS_COST_CODE] SET NEW_COST_CODE_ID = '05-4100', NEW_ITEM_ID = 'Contract Item' WHERE LEGACY_COST_CODE_ID = '05-4100' AND DATA_FOLDER_ID = 'sampl' | G132: =IF(B132<>D132,"Changed","-") -> - | H132: =IF(B132="","Hide","-") -> -
A133: sampl | B133: 05-5000 | C133: Miscellaneous Metals | D133: 05-5000 | E133: Contract Item | F133: ="UPDATE "&F$3&" SET NEW_COST_CODE_ID = '"&D133&"', NEW_ITEM_ID = '"&E133&"' WHERE LEGACY_COST_CODE_ID = '"&B133&"' AND DATA_FOLDER_ID = '"&A133&"'" -> UPDATE [MAP].[T_TRANS_COST_CODE] SET NEW_COST_CODE_ID = '05-5000', NEW_ITEM_ID = 'Contract Item' WHERE LEGACY_COST_CODE_ID = '05-5000' AND DATA_FOLDER_ID = 'sampl' | G133: =IF(B133<>D133,"Changed","-") -> - | H133: =IF(B133="","Hide","-") -> -
A134: sampl | B134: 05-5500 | C134: Cold-Formed Metal Framing | D134: 05-5500 | E134: Contract Item | F134: ="UPDATE "&F$3&" SET NEW_COST_CODE_ID = '"&D134&"', NEW_ITEM_ID = '"&E134&"' WHERE LEGACY_COST_CODE_ID = '"&B134&"' AND DATA_FOLDER_ID = '"&A134&"'" -> UPDATE [MAP].[T_TRANS_COST_CODE] SET NEW_COST_CODE_ID = '05-5500', NEW_ITEM_ID = 'Contract Item' WHERE LEGACY_COST_CODE_ID = '05-5500' AND DATA_FOLDER_ID = 'sampl' | G134: =IF(B134<>D134,"Changed","-") -> - | H134: =IF(B134="","Hide","-") -> -
A135: sampl | B135: 05-7000 | C135: Decorative Metal | D135: 05-7000 | E135: Contract Item | F135: ="UPDATE "&F$3&" SET NEW_COST_CODE_ID = '"&D135&"', NEW_ITEM_ID = '"&E135&"' WHERE LEGACY_COST_CODE_ID = '"&B135&"' AND DATA_FOLDER_ID = '"&A135&"'" -> UPDATE [MAP].[T_TRANS_COST_CODE] SET NEW_COST_CODE_ID = '05-7000', NEW_ITEM_ID = 'Contract Item' WHERE LEGACY_COST_CODE_ID = '05-7000' AND DATA_FOLDER_ID = 'sampl' | G135: =IF(B135<>D135,"Changed","-") -> - | H135: =IF(B135="","Hide","-") -> -
A136: sampl | B136: 06-0000 | C136: WOOD, PLASTICS & COMPOSITES | D136: 06-0000 | F136: ="UPDATE "&F$3&" SET NEW_COST_CODE_ID = '"&D136&"', NEW_ITEM_ID = '"&E136&"' WHERE LEGACY_COST_CODE_ID = '"&B136&"' AND DATA_FOLDER_ID = '"&A136&"'" -> UPDATE [MAP].[T_TRANS_COST_CODE] SET NEW_COST_CODE_ID = '06-0000', NEW_ITEM_ID = ' ' WHERE LEGACY_COST_CODE_ID = '06-0000' AND DATA_FOLDER_ID = 'sampl' | G136: =IF(B136<>D136,"Changed","-") -> - | H136: =IF(B136="","Hide","-") -> -
A137: sampl | B137: 06-1053 | C137: Roof Wood Blocking | D137: 06-1053 | E137: Contract Item | F137: ="UPDATE "&F$3&" SET NEW_COST_CODE_ID = '"&D137&"', NEW_ITEM_ID = '"&E137&"' WHERE LEGACY_COST_CODE_ID = '"&B137&"' AND DATA_FOLDER_ID = '"&A137&"'" -> UPDATE [MAP].[T_TRANS_COST_CODE] SET NEW_COST_CODE_ID = '06-1053', NEW_ITEM_ID = 'Contract Item' WHERE LEGACY_COST_CODE_ID = '06-1053' AND DATA_FOLDER_ID = 'sampl' | G137: =IF(B137<>D137,"Changed","-") -> - | H137: =IF(B137="","Hide","-") -> -
A138: sampl | B138: 06-1054 | C138: In Wall Wood Blocking | D138: 06-1054 | E138: Contract Item | F138: ="UPDATE "&F$3&" SET NEW_COST_CODE_ID = '"&D138&"', NEW_ITEM_ID = '"&E138&"' WHERE LEGACY_COST_CODE_ID = '"&B138&"' AND DATA_FOLDER_ID = '"&A138&"'" -> UPDATE [MAP].[T_TRANS_COST_CODE] SET NEW_COST_CODE_ID = '06-1054', NEW_ITEM_ID = 'Contract Item' WHERE LEGACY_COST_CODE_ID = '06-1054' AND DATA_FOLDER_ID = 'sampl' | G138: =IF(B138<>D138,"Changed","-") -> - | H138: =IF(B138="","Hide","-") -> -
A139: sampl | B139: 06-1055 | C139: In Wall Metal Blocking | D139: 06-1055 | E139: Contract Item | F139: ="UPDATE "&F$3&" SET NEW_COST_CODE_ID = '"&D139&"', NEW_ITEM_ID = '"&E139&"' WHERE LEGACY_COST_CODE_ID = '"&B139&"' AND DATA_FOLDER_ID = '"&A139&"'" -> UPDATE [MAP].[T_TRANS_COST_CODE] SET NEW_COST_CODE_ID = '06-1055', NEW_ITEM_ID = 'Contract Item' WHERE LEGACY_COST_CODE_ID = '06-1055' AND DATA_FOLDER_ID = 'sampl' | G139: =IF(B139<>D139,"Changed","-") -> - | H139: =IF(B139="","Hide","-") -> -
A140: sampl | B140: 06-1056 | C140: Wood Sheathing | D140: 06-1056 | E140: Contract Item | F140: ="UPDATE "&F$3&" SET NEW_COST_CODE_ID = '"&D140&"', NEW_ITEM_ID = '"&E140&"' WHERE LEGACY_COST_CODE_ID = '"&B140&"' AND DATA_FOLDER_ID = '"&A140&"'" -> UPDATE [MAP].[T_TRANS_COST_CODE] SET NEW_COST_CODE_ID = '06-1056', NEW_ITEM_ID = 'Contract Item' WHERE LEGACY_COST_CODE_ID = '06-1056' AND DATA_FOLDER_ID = 'sampl' | G140: =IF(B140<>D140,"Changed","-") -> - | H140: =IF(B140="","Hide","-") -> -
A141: sampl | B141: 06-1110 | C141: Wood Framing, Flooring | D141: 06-1110 | E141: Contract Item | F141: ="UPDATE "&F$3&" SET NEW_COST_CODE_ID = '"&D141&"', NEW_ITEM_ID = '"&E141&"' WHERE LEGACY_COST_CODE_ID = '"&B141&"' AND DATA_FOLDER_ID = '"&A141&"'" -> UPDATE [MAP].[T_TRANS_COST_CODE] SET NEW_COST_CODE_ID = '06-1110', NEW_ITEM_ID = 'Contract Item' WHERE LEGACY_COST_CODE_ID = '06-1110' AND DATA_FOLDER_ID = 'sampl' | G141: =IF(B141<>D141,"Changed","-") -> - | H141: =IF(B141="","Hide","-") -> -
A142: sampl | B142: 06-1120 | C142: Wood Framing, Walls | D142: 06-1120 | E142: Contract Item | F142: ="UPDATE "&F$3&" SET NEW_COST_CODE_ID = '"&D142&"', NEW_ITEM_ID = '"&E142&"' WHERE LEGACY_COST_CODE_ID = '"&B142&"' AND DATA_FOLDER_ID = '"&A142&"'" -> UPDATE [MAP].[T_TRANS_COST_CODE] SET NEW_COST_CODE_ID = '06-1120', NEW_ITEM_ID = 'Contract Item' WHERE LEGACY_COST_CODE_ID = '06-1120' AND DATA_FOLDER_ID = 'sampl' | G142: =IF(B142<>D142,"Changed","-") -> - | H142: =IF(B142="","Hide","-") -> -
A143: sampl | B143: 06-1130 | C143: Wood Framing, Ceilings | D143: 06-1130 | E143: Contract Item | F143: ="UPDATE "&F$3&" SET NEW_COST_CODE_ID = '"&D143&"', NEW_ITEM_ID = '"&E143&"' WHERE LEGACY_COST_CODE_ID = '"&B143&"' AND DATA_FOLDER_ID = '"&A143&"'" -> UPDATE [MAP].[T_TRANS_COST_CODE] SET NEW_COST_CODE_ID = '06-1130', NEW_ITEM_ID = 'Contract Item' WHERE LEGACY_COST_CODE_ID = '06-1130' AND DATA_FOLDER_ID = 'sampl' | G143: =IF(B143<>D143,"Changed","-") -> - | H143: =IF(B143="","Hide","-") -> -
A144: sampl | B144: 06-1140 | C144: Wood Framing, Roofing | D144: 06-1140 | E144: Contract Item | F144: ="UPDATE "&F$3&" SET NEW_COST_CODE_ID = '"&D144&"', NEW_ITEM_ID = '"&E144&"' WHERE LEGACY_COST_CODE_ID = '"&B144&"' AND DATA_FOLDER_ID = '"&A144&"'" -> UPDATE [MAP].[T_TRANS_COST_CODE] SET NEW_COST_CODE_ID = '06-1140', NEW_ITEM_ID = 'Contract Item' WHERE LEGACY_COST_CODE_ID = '06-1140' AND DATA_FOLDER_ID = 'sampl' | G144: =IF(B144<>D144,"Changed","-") -> - | H144: =IF(B144="","Hide","-") -> -
A145: sampl | B145: 06-1300 | C145: Heavy Timber Construction | D145: 06-1300 | E145: Contract Item | F145: ="UPDATE "&F$3&" SET NEW_COST_CODE_ID = '"&D145&"', NEW_ITEM_ID = '"&E145&"' WHERE LEGACY_COST_CODE_ID = '"&B145&"' AND DATA_FOLDER_ID = '"&A145&"'" -> UPDATE [MAP].[T_TRANS_COST_CODE] SET NEW_COST_CODE_ID = '06-1300', NEW_ITEM_ID = 'Contract Item' WHERE LEGACY_COST_CODE_ID = '06-1300' AND DATA_FOLDER_ID = 'sampl' | G145: =IF(B145<>D145,"Changed","-") -> - | H145: =IF(B145="","Hide","-") -> -
A146: sampl | B146: 06-1713 | C146: Laminated Veneer Lumber | D146: 06-1713 | E146: Contract Item | F146: ="UPDATE "&F$3&" SET NEW_COST_CODE_ID = '"&D146&"', NEW_ITEM_ID = '"&E146&"' WHERE LEGACY_COST_CODE_ID = '"&B146&"' AND DATA_FOLDER_ID = '"&A146&"'" -> UPDATE [MAP].[T_TRANS_COST_CODE] SET NEW_COST_CODE_ID = '06-1713', NEW_ITEM_ID = 'Contract Item' WHERE LEGACY_COST_CODE_ID = '06-1713' AND DATA_FOLDER_ID = 'sampl' | G146: =IF(B146<>D146,"Changed","-") -> - | H146: =IF(B146="","Hide","-") -> -
A147: sampl | B147: 06-1753 | C147: Wood Trusses | D147: 06-1753 | E147: Contract Item | F147: ="UPDATE "&F$3&" SET NEW_COST_CODE_ID = '"&D147&"', NEW_ITEM_ID = '"&E147&"' WHERE LEGACY_COST_CODE_ID = '"&B147&"' AND DATA_FOLDER_ID = '"&A147&"'" -> UPDATE [MAP].[T_TRANS_COST_CODE] SET NEW_COST_CODE_ID = '06-1753', NEW_ITEM_ID = 'Contract Item' WHERE LEGACY_COST_CODE_ID = '06-1753' AND DATA_FOLDER_ID = 'sampl' | G147: =IF(B147<>D147,"Changed","-") -> - | H147: =IF(B147="","Hide","-") -> -
A148: sampl | B148: 06-2000 | C148: Carpenter Foreman | D148: 06-2000 | E148: Contract Item | F148: ="UPDATE "&F$3&" SET NEW_COST_CODE_ID = '"&D148&"', NEW_ITEM_ID = '"&E148&"' WHERE LEGACY_COST_CODE_ID = '"&B148&"' AND DATA_FOLDER_ID = '"&A148&"'" -> UPDATE [MAP].[T_TRANS_COST_CODE] SET NEW_COST_CODE_ID = '06-2000', NEW_ITEM_ID = 'Contract Item' WHERE LEGACY_COST_CODE_ID = '06-2000' AND DATA_FOLDER_ID = 'sampl' | G148: =IF(B148<>D148,"Changed","-") -> - | H148: =IF(B148="","Hide","-") -> -
... A157: sampl | B157: 06-4800 | C157: Wood Frames | D157: 06-4800 | E157: Contract Item | F157: ="UPDATE "&F$3&" SET NEW_COST_CODE_ID = '"&D157&"', NEW_ITEM_ID = '"&E157&"' WHERE LEGACY_COST_CODE_ID = '"&B157&"' AND DATA_FOLDER_ID = '"&A157&"'" -> UPDATE [MAP].[T_TRANS_COST_CODE] SET NEW_COST_CODE_ID = '06-4800', NEW_ITEM_ID = 'Contract Item' WHERE LEGACY_COST_CODE_ID = '06-4800' AND DATA_FOLDER_ID = 'sampl' | G157: =IF(B157<>D157,"Changed","-") -> - | H157: =IF(B157="","Hide","-") -> -
A158: sampl | B158: 07-0000 | C158: THERMAL & MOISTURE PROTECTION | D158: 07-0000 | F158: ="UPDATE "&F$3&" SET NEW_COST_CODE_ID = '"&D158&"', NEW_ITEM_ID = '"&E158&"' WHERE LEGACY_COST_CODE_ID = '"&B158&"' AND DATA_FOLDER_ID = '"&A158&"'" -> UPDATE [MAP].[T_TRANS_COST_CODE] SET NEW_COST_CODE_ID = '07-0000', NEW_ITEM_ID = ' ' WHERE LEGACY_COST_CODE_ID = '07-0000' AND DATA_FOLDER_ID = 'sampl' | G158: =IF(B158<>D158,"Changed","-") -> - | H158: =IF(B158="","Hide","-") -> -
A159: sampl | B159: 07-1000 | C159: Dampproofing & Waterproofing | D159: 07-1000 | E159: Contract Item | F159: ="UPDATE "&F$3&" SET NEW_COST_CODE_ID = '"&D159&"', NEW_ITEM_ID = '"&E159&"' WHERE LEGACY_COST_CODE_ID = '"&B159&"' AND DATA_FOLDER_ID = '"&A159&"'" -> UPDATE [MAP].[T_TRANS_COST_CODE] SET NEW_COST_CODE_ID = '07-1000', NEW_ITEM_ID = 'Contract Item' WHERE LEGACY_COST_CODE_ID = '07-1000' AND DATA_FOLDER_ID = 'sampl' | G159: =IF(B159<>D159,"Changed","-") -> - | H159: =IF(B159="","Hide","-") -> -
A160: sampl | B160: 07-2100 | C160: Insulation | D160: 07-2100 | E160: Contract Item | F160: ="UPDATE "&F$3&" SET NEW_COST_CODE_ID = '"&D160&"', NEW_ITEM_ID = '"&E160&"' WHERE LEGACY_COST_CODE_ID = '"&B160&"' AND DATA_FOLDER_ID = '"&A160&"'" -> UPDATE [MAP].[T_TRANS_COST_CODE] SET NEW_COST_CODE_ID = '07-2100', NEW_ITEM_ID = 'Contract Item' WHERE LEGACY_COST_CODE_ID = '07-2100' AND DATA_FOLDER_ID = 'sampl' | G160: =IF(B160<>D160,"Changed","-") -> - | H160: =IF(B160="","Hide","-") -> -
A161: sampl | B161: 07-2400 | C161: EIFS | D161: 07-2400 | E161: Contract Item | F161: ="UPDATE "&F$3&" SET NEW_COST_CODE_ID = '"&D161&"', NEW_ITEM_ID = '"&E161&"' WHERE LEGACY_COST_CODE_ID = '"&B161&"' AND DATA_FOLDER_ID = '"&A161&"'" -> UPDATE [MAP].[T_TRANS_COST_CODE] SET NEW_COST_CODE_ID = '07-2400', NEW_ITEM_ID = 'Contract Item' WHERE LEGACY_COST_CODE_ID = '07-2400' AND DATA_FOLDER_ID = 'sampl' | G161: =IF(B161<>D161,"Changed","-") -> - | H161: =IF(B161="","Hide","-") -> -
A162: sampl | B162: 07-2700 | C162: Air Barrier | D162: 07-2700 | E162: Contract Item | F162: ="UPDATE "&F$3&" SET NEW_COST_CODE_ID = '"&D162&"', NEW_ITEM_ID = '"&E162&"' WHERE LEGACY_COST_CODE_ID = '"&B162&"' AND DATA_FOLDER_ID = '"&A162&"'" -> UPDATE [MAP].[T_TRANS_COST_CODE] SET NEW_COST_CODE_ID = '07-2700', NEW_ITEM_ID = 'Contract Item' WHERE LEGACY_COST_CODE_ID = '07-2700' AND DATA_FOLDER_ID = 'sampl' | G162: =IF(B162<>D162,"Changed","-") -> - | H162: =IF(B162="","Hide","-") -> -
A163: sampl | B163: 07-3100 | C163: Shingles & Shakes | D163: 07-3100 | E163: Contract Item | F163: ="UPDATE "&F$3&" SET NEW_COST_CODE_ID = '"&D163&"', NEW_ITEM_ID = '"&E163&"' WHERE LEGACY_COST_CODE_ID = '"&B163&"' AND DATA_FOLDER_ID = '"&A163&"'" -> UPDATE [MAP].[T_TRANS_COST_CODE] SET NEW_COST_CODE_ID = '07-3100', NEW_ITEM_ID = 'Contract Item' WHERE LEGACY_COST_CODE_ID = '07-3100' AND DATA_FOLDER_ID = 'sampl' | G163: =IF(B163<>D163,"Changed","-") -> - | H163: =IF(B163="","Hide","-") -> -
A164: sampl | B164: 07-4100 | C164: Roof Panels | D164: 07-4100 | E164: Contract Item | F164: ="UPDATE "&F$3&" SET NEW_COST_CODE_ID = '"&D164&"', NEW_ITEM_ID = '"&E164&"' WHERE LEGACY_COST_CODE_ID = '"&B164&"' AND DATA_FOLDER_ID = '"&A164&"'" -> UPDATE [MAP].[T_TRANS_COST_CODE] SET NEW_COST_CODE_ID = '07-4100', NEW_ITEM_ID = 'Contract Item' WHERE LEGACY_COST_CODE_ID = '07-4100' AND DATA_FOLDER_ID = 'sampl' | G164: =IF(B164<>D164,"Changed","-") -> - | H164: =IF(B164="","Hide","-") -> -
A165: sampl | B165: 07-4200 | C165: Wall Panels | D165: 07-4200 | E165: Contract Item | F165: ="UPDATE "&F$3&" SET NEW_COST_CODE_ID = '"&D165&"', NEW_ITEM_ID = '"&E165&"' WHERE LEGACY_COST_CODE_ID = '"&B165&"' AND DATA_FOLDER_ID = '"&A165&"'" -> UPDATE [MAP].[T_TRANS_COST_CODE] SET NEW_COST_CODE_ID = '07-4200', NEW_ITEM_ID = 'Contract Item' WHERE LEGACY_COST_CODE_ID = '07-4200' AND DATA_FOLDER_ID = 'sampl' | G165: =IF(B165<>D165,"Changed","-") -> - | H165: =IF(B165="","Hide","-") -> -
A166: sampl | B166: 07-4213 | C166: Insulated Metal Panels | D166: 07-4213 | E166: Contract Item | F166: ="UPDATE "&F$3&" SET NEW_COST_CODE_ID = '"&D166&"', NEW_ITEM_ID = '"&E166&"' WHERE LEGACY_COST_CODE_ID = '"&B166&"' AND DATA_FOLDER_ID = '"&A166&"'" -> UPDATE [MAP].[T_TRANS_COST_CODE] SET NEW_COST_CODE_ID = '07-4213', NEW_ITEM_ID = 'Contract Item' WHERE LEGACY_COST_CODE_ID = '07-4213' AND DATA_FOLDER_ID = 'sampl' | G166: =IF(B166<>D166,"Changed","-") -> - | H166: =IF(B166="","Hide","-") -> -
A167: sampl | B167: 07-4263 | C167: Fabricated Wall Panel Assy | D167: 07-4263 | E167: Contract Item | F167: ="UPDATE "&F$3&" SET NEW_COST_CODE_ID = '"&D167&"', NEW_ITEM_ID = '"&E167&"' WHERE LEGACY_COST_CODE_ID = '"&B167&"' AND DATA_FOLDER_ID = '"&A167&"'" -> UPDATE [MAP].[T_TRANS_COST_CODE] SET NEW_COST_CODE_ID = '07-4263', NEW_ITEM_ID = 'Contract Item' WHERE LEGACY_COST_CODE_ID = '07-4263' AND DATA_FOLDER_ID = 'sampl' | G167: =IF(B167<>D167,"Changed","-") -> - | H167: =IF(B167="","Hide","-") -> -
A168: sampl | B168: 07-4600 | C168: Siding | D168: 07-4600 | E168: Contract Item | F168: ="UPDATE "&F$3&" SET NEW_COST_CODE_ID = '"&D168&"', NEW_ITEM_ID = '"&E168&"' WHERE LEGACY_COST_CODE_ID = '"&B168&"' AND DATA_FOLDER_ID = '"&A168&"'" -> UPDATE [MAP].[T_TRANS_COST_CODE] SET NEW_COST_CODE_ID = '07-4600', NEW_ITEM_ID = 'Contract Item' WHERE LEGACY_COST_CODE_ID = '07-4600' AND DATA_FOLDER_ID = 'sampl' | G168: =IF(B168<>D168,"Changed","-") -> - | H168: =IF(B168="","Hide","-") -> -
A169: sampl | B169: 07-5000 | C169: Membrane Roofing | D169: 07-5000 | E169: Contract Item | F169: ="UPDATE "&F$3&" SET NEW_COST_CODE_ID = '"&D169&"', NEW_ITEM_ID = '"&E169&"' WHERE LEGACY_COST_CODE_ID = '"&B169&"' AND DATA_FOLDER_ID = '"&A169&"'" -> UPDATE [MAP].[T_TRANS_COST_CODE] SET NEW_COST_CODE_ID = '07-5000', NEW_ITEM_ID = 'Contract Item' WHERE LEGACY_COST_CODE_ID = '07-5000' AND DATA_FOLDER_ID = 'sampl' | G169: =IF(B169<>D169,"Changed","-") -> - | H169: =IF(B169="","Hide","-") -> -
A170: sampl | B170: 07-6000 | C170: Flashing & Sheet Metal | D170: 07-6000 | E170: Contract Item | F170: ="UPDATE "&F$3&" SET NEW_COST_CODE_ID = '"&D170&"', NEW_ITEM_ID = '"&E170&"' WHERE LEGACY_COST_CODE_ID = '"&B170&"' AND DATA_FOLDER_ID = '"&A170&"'" -> UPDATE [MAP].[T_TRANS_COST_CODE] SET NEW_COST_CODE_ID = '07-6000', NEW_ITEM_ID = 'Contract Item' WHERE LEGACY_COST_CODE_ID = '07-6000' AND DATA_FOLDER_ID = 'sampl' | G170: =IF(B170<>D170,"Changed","-") -> - | H170: =IF(B170="","Hide","-") -> -
... A176: sampl | B176: 07-9500 | C176: Expansion Control | D176: 07-9500 | E176: Contract Item | F176: ="UPDATE "&F$3&" SET NEW_COST_CODE_ID = '"&D176&"', NEW_ITEM_ID = '"&E176&"' WHERE LEGACY_COST_CODE_ID = '"&B176&"' AND DATA_FOLDER_ID = '"&A176&"'" -> UPDATE [MAP].[T_TRANS_COST_CODE] SET NEW_COST_CODE_ID = '07-9500', NEW_ITEM_ID = 'Contract Item' WHERE LEGACY_COST_CODE_ID = '07-9500' AND DATA_FOLDER_ID = 'sampl' | G176: =IF(B176<>D176,"Changed","-") -> - | H176: =IF(B176="","Hide","-") -> -
A177: sampl | B177: 08-0000 | C177: OPENINGS | D177: 08-0000 | F177: ="UPDATE "&F$3&" SET NEW_COST_CODE_ID = '"&D177&"', NEW_ITEM_ID = '"&E177&"' WHERE LEGACY_COST_CODE_ID = '"&B177&"' AND DATA_FOLDER_ID = '"&A177&"'" -> UPDATE [MAP].[T_TRANS_COST_CODE] SET NEW_COST_CODE_ID = '08-0000', NEW_ITEM_ID = ' ' WHERE LEGACY_COST_CODE_ID = '08-0000' AND DATA_FOLDER_ID = 'sampl' | G177: =IF(B177<>D177,"Changed","-") -> - | H177: =IF(B177="","Hide","-") -> -
A178: sampl | B178: 08-1100 | C178: Door Frames | D178: 08-1100 | E178: Contract Item | F178: ="UPDATE "&F$3&" SET NEW_COST_CODE_ID = '"&D178&"', NEW_ITEM_ID = '"&E178&"' WHERE LEGACY_COST_CODE_ID = '"&B178&"' AND DATA_FOLDER_ID = '"&A178&"'" -> UPDATE [MAP].[T_TRANS_COST_CODE] SET NEW_COST_CODE_ID = '08-1100', NEW_ITEM_ID = 'Contract Item' WHERE LEGACY_COST_CODE_ID = '08-1100' AND DATA_FOLDER_ID = 'sampl' | G178: =IF(B178<>D178,"Changed","-") -> - | H178: =IF(B178="","Hide","-") -> -
A179: sampl | B179: 08-1101 | C179: Door Leaf's | D179: 08-1101 | E179: Contract Item | F179: ="UPDATE "&F$3&" SET NEW_COST_CODE_ID = '"&D179&"', NEW_ITEM_ID = '"&E179&"' WHERE LEGACY_COST_CODE_ID = '"&B179&"' AND DATA_FOLDER_ID = '"&A179&"'" -> UPDATE [MAP].[T_TRANS_COST_CODE] SET NEW_COST_CODE_ID = '08-1101', NEW_ITEM_ID = 'Contract Item' WHERE LEGACY_COST_CODE_ID = '08-1101' AND DATA_FOLDER_ID = 'sampl' | G179: =IF(B179<>D179,"Changed","-") -> - | H179: =IF(B179="","Hide","-") -> -
A180: sampl | B180: 08-1102 | C180: Door Hardware | D180: 08-1102 | E180: Contract Item | F180: ="UPDATE "&F$3&" SET NEW_COST_CODE_ID = '"&D180&"', NEW_ITEM_ID = '"&E180&"' WHERE LEGACY_COST_CODE_ID = '"&B180&"' AND DATA_FOLDER_ID = '"&A180&"'" -> UPDATE [MAP].[T_TRANS_COST_CODE] SET NEW_COST_CODE_ID = '08-1102', NEW_ITEM_ID = 'Contract Item' WHERE LEGACY_COST_CODE_ID = '08-1102' AND DATA_FOLDER_ID = 'sampl' | G180: =IF(B180<>D180,"Changed","-") -> - | H180: =IF(B180="","Hide","-") -> -
A181: sampl | B181: 08-1103 | C181: Speciality Opening | D181: 08-1103 | E181: Contract Item | F181: ="UPDATE "&F$3&" SET NEW_COST_CODE_ID = '"&D181&"', NEW_ITEM_ID = '"&E181&"' WHERE LEGACY_COST_CODE_ID = '"&B181&"' AND DATA_FOLDER_ID = '"&A181&"'" -> UPDATE [MAP].[T_TRANS_COST_CODE] SET NEW_COST_CODE_ID = '08-1103', NEW_ITEM_ID = 'Contract Item' WHERE LEGACY_COST_CODE_ID = '08-1103' AND DATA_FOLDER_ID = 'sampl' | G181: =IF(B181<>D181,"Changed","-") -> - | H181: =IF(B181="","Hide","-") -> -
A182: sampl | B182: 08-3100 | C182: Access Doors & Panels | D182: 08-3100 | E182: Contract Item | F182: ="UPDATE "&F$3&" SET NEW_COST_CODE_ID = '"&D182&"', NEW_ITEM_ID = '"&E182&"' WHERE LEGACY_COST_CODE_ID = '"&B182&"' AND DATA_FOLDER_ID = '"&A182&"'" -> UPDATE [MAP].[T_TRANS_COST_CODE] SET NEW_COST_CODE_ID = '08-3100', NEW_ITEM_ID = 'Contract Item' WHERE LEGACY_COST_CODE_ID = '08-3100' AND DATA_FOLDER_ID = 'sampl' | G182: =IF(B182<>D182,"Changed","-") -> - | H182: =IF(B182="","Hide","-") -> -
A183: sampl | B183: 08-3600 | C183: Overhead Doors | D183: 08-3600 | E183: Contract Item | F183: ="UPDATE "&F$3&" SET NEW_COST_CODE_ID = '"&D183&"', NEW_ITEM_ID = '"&E183&"' WHERE LEGACY_COST_CODE_ID = '"&B183&"' AND DATA_FOLDER_ID = '"&A183&"'" -> UPDATE [MAP].[T_TRANS_COST_CODE] SET NEW_COST_CODE_ID = '08-3600', NEW_ITEM_ID = 'Contract Item' WHERE LEGACY_COST_CODE_ID = '08-3600' AND DATA_FOLDER_ID = 'sampl' | G183: =IF(B183<>D183,"Changed","-") -> - | H183: =IF(B183="","Hide","-") -> -
...

Sheet Cost Type ID
A1: ="Legacy ERP: "&Controls!$B$2 -> Legacy ERP: Sage 300 CRE | D1: ="New ERP: "&Controls!$B$3 -> New ERP: Sage Intacct
A3: Data Folder ID | B3: Cost Type | C3: Cost Type Description | D3: Cost Type | E3: Item ID | F3: GL Account | G3: [MAP].[T_TRANS_COST_TYPE] | H3: Change | I3: hide/show
A4: sampl | B4: E | C4: Equipment Rented | D4: E | E4: E | F4: 5205 | G4: ="UPDATE "&G$3&" SET NEW_COST_TYPE_ID = '"&D4&"', NEW_ITEM_ID = '"&E4&"', NEW_INTACCT_GL_ACCOUNT = '"&F4&"' WHERE LEGACY_COST_TYPE_ID = '"&B4&"' AND DATA_FOLDER_ID = '"&A4&"'" -> UPDATE [MAP].[T_TRANS_COST_TYPE] SET NEW_COST_TYPE_ID = 'E', NEW_ITEM_ID = 'E', NEW_INTACCT_GL_ACCOUNT = '5205' WHERE LEGACY_COST_TYPE_ID = 'E' AND DATA_FOLDER_ID = 'sampl' | H4: =IF(B4<>D4,"Changed","-") -> - | I4: =IF(B4="","Hide","-") -> -
A5: sampl | B5: EO | C5: Equipment Owned | D5: EO | E5: EO | F5: 5200 | G5: ="UPDATE "&G$3&" SET NEW_COST_TYPE_ID = '"&D5&"', NEW_ITEM_ID = '"&E5&"', NEW_INTACCT_GL_ACCOUNT = '"&F5&"' WHERE LEGACY_COST_TYPE_ID = '"&B5&"' AND DATA_FOLDER_ID = '"&A5&"'" -> UPDATE [MAP].[T_TRANS_COST_TYPE] SET NEW_COST_TYPE_ID = 'EO', NEW_ITEM_ID = 'EO', NEW_INTACCT_GL_ACCOUNT = '5200' WHERE LEGACY_COST_TYPE_ID = 'EO' AND DATA_FOLDER_ID = 'sampl' | H5: =IF(B5<>D5,"Changed","-") -> - | I5: =IF(B5="","Hide","-") -> -
A6: sampl | B6: FT | C6: Freight & Sales Tax | D6: FT | E6: FT | F6: 5100 | G6: ="UPDATE "&G$3&" SET NEW_COST_TYPE_ID = '"&D6&"', NEW_ITEM_ID = '"&E6&"', NEW_INTACCT_GL_ACCOUNT = '"&F6&"' WHERE LEGACY_COST_TYPE_ID = '"&B6&"' AND DATA_FOLDER_ID = '"&A6&"'" -> UPDATE [MAP].[T_TRANS_COST_TYPE] SET NEW_COST_TYPE_ID = 'FT', NEW_ITEM_ID = 'FT', NEW_INTACCT_GL_ACCOUNT = '5100' WHERE LEGACY_COST_TYPE_ID = 'FT' AND DATA_FOLDER_ID = 'sampl' | H6: =IF(B6<>D6,"Changed","-") -> - | I6: =IF(B6="","Hide","-") -> -
A7: sampl | B7: IDE | C7: Insurance Dental Employee (DNU) | D7: IDE | E7: L | F7: 5020 | G7: ="UPDATE "&G$3&" SET NEW_COST_TYPE_ID = '"&D7&"', NEW_ITEM_ID = '"&E7&"', NEW_INTACCT_GL_ACCOUNT = '"&F7&"' WHERE LEGACY_COST_TYPE_ID = '"&B7&"' AND DATA_FOLDER_ID = '"&A7&"'" -> UPDATE [MAP].[T_TRANS_COST_TYPE] SET NEW_COST_TYPE_ID = 'IDE', NEW_ITEM_ID = 'L', NEW_INTACCT_GL_ACCOUNT = '5020' WHERE LEGACY_COST_TYPE_ID = 'IDE' AND DATA_FOLDER_ID = 'sampl' | H7: =IF(B7<>D7,"Changed","-") -> - | I7: =IF(B7="","Hide","-") -> -
A8: sampl | B8: IDI | C8: Insurance STD Employee (DNU) | D8: IDI | E8: L | F8: 5020 | G8: ="UPDATE "&G$3&" SET NEW_COST_TYPE_ID = '"&D8&"', NEW_ITEM_ID = '"&E8&"', NEW_INTACCT_GL_ACCOUNT = '"&F8&"' WHERE LEGACY_COST_TYPE_ID = '"&B8&"' AND DATA_FOLDER_ID = '"&A8&"'" -> UPDATE [MAP].[T_TRANS_COST_TYPE] SET NEW_COST_TYPE_ID = 'IDI', NEW_ITEM_ID = 'L', NEW_INTACCT_GL_ACCOUNT = '5020' WHERE LEGACY_COST_TYPE_ID = 'IDI' AND DATA_FOLDER_ID = 'sampl' | H8: =IF(B8<>D8,"Changed","-") -> - | I8: =IF(B8="","Hide","-") -> -
A9: sampl | B9: IHE | C9: Insurance Health Employee (DNU) | D9: IHE | E9: L | F9: 5020 | G9: ="UPDATE "&G$3&" SET NEW_COST_TYPE_ID = '"&D9&"', NEW_ITEM_ID = '"&E9&"', NEW_INTACCT_GL_ACCOUNT = '"&F9&"' WHERE LEGACY_COST_TYPE_ID = '"&B9&"' AND DATA_FOLDER_ID = '"&A9&"'" -> UPDATE [MAP].[T_TRANS_COST_TYPE] SET NEW_COST_TYPE_ID = 'IHE', NEW_ITEM_ID = 'L', NEW_INTACCT_GL_ACCOUNT = '5020' WHERE LEGACY_COST_TYPE_ID = 'IHE' AND DATA_FOLDER_ID = 'sampl' | H9: =IF(B9<>D9,"Changed","-") -> - | I9: =IF(B9="","Hide","-") -> -
A10: sampl | B10: ILI | C10: Insurance Life Employee (DNU) | D10: ILI | E10: L | F10: 5020 | G10: ="UPDATE "&G$3&" SET NEW_COST_TYPE_ID = '"&D10&"', NEW_ITEM_ID = '"&E10&"', NEW_INTACCT_GL_ACCOUNT = '"&F10&"' WHERE LEGACY_COST_TYPE_ID = '"&B10&"' AND DATA_FOLDER_ID = '"&A10&"'" -> UPDATE [MAP].[T_TRANS_COST_TYPE] SET NEW_COST_TYPE_ID = 'ILI', NEW_ITEM_ID = 'L', NEW_INTACCT_GL_ACCOUNT = '5020' WHERE LEGACY_COST_TYPE_ID = 'ILI' AND DATA_FOLDER_ID = 'sampl' | H10: =IF(B10<>D10,"Changed","-") -> - | I10: =IF(B10="","Hide","-") -> -
A11: sampl | B11: L | C11: Labor | D11: L | E11: L | F11: 5000 | G11: ="UPDATE "&G$3&" SET NEW_COST_TYPE_ID = '"&D11&"', NEW_ITEM_ID = '"&E11&"', NEW_INTACCT_GL_ACCOUNT = '"&F11&"' WHERE LEGACY_COST_TYPE_ID = '"&B11&"' AND DATA_FOLDER_ID = '"&A11&"'" -> UPDATE [MAP].[T_TRANS_COST_TYPE] SET NEW_COST_TYPE_ID = 'L', NEW_ITEM_ID = 'L', NEW_INTACCT_GL_ACCOUNT = '5000' WHERE LEGACY_COST_TYPE_ID = 'L' AND DATA_FOLDER_ID = 'sampl' | H11: =IF(B11<>D11,"Changed","-") -> - | I11: =IF(B11="","Hide","-") -> -
A12: sampl | B12: LFT | C12: FICA Withholding Tax (DNU) | D12: LFT | E12: L | F12: 5005 | G12: ="UPDATE "&G$3&" SET NEW_COST_TYPE_ID = '"&D12&"', NEW_ITEM_ID = '"&E12&"', NEW_INTACCT_GL_ACCOUNT = '"&F12&"' WHERE LEGACY_COST_TYPE_ID = '"&B12&"' AND DATA_FOLDER_ID = '"&A12&"'" -> UPDATE [MAP].[T_TRANS_COST_TYPE] SET NEW_COST_TYPE_ID = 'LFT', NEW_ITEM_ID = 'L', NEW_INTACCT_GL_ACCOUNT = '5005' WHERE LEGACY_COST_TYPE_ID = 'LFT' AND DATA_FOLDER_ID = 'sampl' | H12: =IF(B12<>D12,"Changed","-") -> - | I12: =IF(B12="","Hide","-") -> -
A13: sampl | B13: LFU | C13: FUTA Unemployment Tax (DNU) | D13: LFU | E13: L | F13: 5005 | G13: ="UPDATE "&G$3&" SET NEW_COST_TYPE_ID = '"&D13&"', NEW_ITEM_ID = '"&E13&"', NEW_INTACCT_GL_ACCOUNT = '"&F13&"' WHERE LEGACY_COST_TYPE_ID = '"&B13&"' AND DATA_FOLDER_ID = '"&A13&"'" -> UPDATE [MAP].[T_TRANS_COST_TYPE] SET NEW_COST_TYPE_ID = 'LFU', NEW_ITEM_ID = 'L', NEW_INTACCT_GL_ACCOUNT = '5005' WHERE LEGACY_COST_TYPE_ID = 'LFU' AND DATA_FOLDER_ID = 'sampl' | H13: =IF(B13<>D13,"Changed","-") -> - | I13: =IF(B13="","Hide","-") -> -
A14: sampl | B14: LPS | C14: Pension Profit Sharing (DNU) | D14: LPS | E14: L | F14: 5010 | G14: ="UPDATE "&G$3&" SET NEW_COST_TYPE_ID = '"&D14&"', NEW_ITEM_ID = '"&E14&"', NEW_INTACCT_GL_ACCOUNT = '"&F14&"' WHERE LEGACY_COST_TYPE_ID = '"&B14&"' AND DATA_FOLDER_ID = '"&A14&"'" -> UPDATE [MAP].[T_TRANS_COST_TYPE] SET NEW_COST_TYPE_ID = 'LPS', NEW_ITEM_ID = 'L', NEW_INTACCT_GL_ACCOUNT = '5010' WHERE LEGACY_COST_TYPE_ID = 'LPS' AND DATA_FOLDER_ID = 'sampl' | H14: =IF(B14<>D14,"Changed","-") -> - | I14: =IF(B14="","Hide","-") -> -
A15: sampl | B15: LSD | C15: State Disability Insurance (DNU) | D15: LSD | E15: L | F15: 5005 | G15: ="UPDATE "&G$3&" SET NEW_COST_TYPE_ID = '"&D15&"', NEW_ITEM_ID = '"&E15&"', NEW_INTACCT_GL_ACCOUNT = '"&F15&"' WHERE LEGACY_COST_TYPE_ID = '"&B15&"' AND DATA_FOLDER_ID = '"&A15&"'" -> UPDATE [MAP].[T_TRANS_COST_TYPE] SET NEW_COST_TYPE_ID = 'LSD', NEW_ITEM_ID = 'L', NEW_INTACCT_GL_ACCOUNT = '5005' WHERE LEGACY_COST_TYPE_ID = 'LSD' AND DATA_FOLDER_ID = 'sampl' | H15: =IF(B15<>D15,"Changed","-") -> - | I15: =IF(B15="","Hide","-") -> -
... A26: sampl | B26: S | C26: Subcontractors | D26: S | E26: S | F26: 5110 | G26: ="UPDATE "&G$3&" SET NEW_COST_TYPE_ID = '"&D26&"', NEW_ITEM_ID = '"&E26&"', NEW_INTACCT_GL_ACCOUNT = '"&F26&"' WHERE LEGACY_COST_TYPE_ID = '"&B26&"' AND DATA_FOLDER_ID = '"&A26&"'" -> UPDATE [MAP].[T_TRANS_COST_TYPE] SET NEW_COST_TYPE_ID = 'S', NEW_ITEM_ID = 'S', NEW_INTACCT_GL_ACCOUNT = '5110' WHERE LEGACY_COST_TYPE_ID = 'S' AND DATA_FOLDER_ID = 'sampl' | H26: =IF(B26<>D26,"Changed","-") -> - | I26: =IF(B26="","Hide","-") -> -

Sheet Employee ID
A1: ="Legacy ERP: "&Controls!$B$2 -> Legacy ERP: Sage 300 CRE | D1: ="New ERP: "&Controls!$B$3 -> New ERP: Sage Intacct
A3: Data Folder ID | B3: Employee | C3: Employee Description | D3: Employee | E3: [MAP].[T_TRANS_EMPLOYEE] | F3: Change | G3: hide/show
A4: sampl | B4: EE1 | C4: John Smith | D4: E0001 | E4: ="UPDATE "&$E$3&" SET NEW_EMPLOYEE_ID = '"&D4&"' WHERE LEGACY_EMPLOYEE_ID = '"&B4&"' AND DATA_FOLDER_ID = '"&$A4&"'" -> UPDATE [MAP].[T_TRANS_EMPLOYEE] SET NEW_EMPLOYEE_ID = 'E0001' WHERE LEGACY_EMPLOYEE_ID = 'EE1' AND DATA_FOLDER_ID = 'sampl' | F4: =IF(B4<>D4,"Changed","-") -> Changed | G4: =IF(B4="","Hide","-") -> -
A5: sampl | B5: EE2 | C5: James Smith | D5: E0002 | E5: ="UPDATE "&$E$3&" SET NEW_EMPLOYEE_ID = '"&D5&"' WHERE LEGACY_EMPLOYEE_ID = '"&B5&"' AND DATA_FOLDER_ID = '"&$A5&"'" -> UPDATE [MAP].[T_TRANS_EMPLOYEE] SET NEW_EMPLOYEE_ID = 'E0002' WHERE LEGACY_EMPLOYEE_ID = 'EE2' AND DATA_FOLDER_ID = 'sampl' | F5: =IF(B5<>D5,"Changed","-") -> Changed | G5: =IF(B5="","Hide","-") -> -
A6: sampl | B6: EE3 | C6: Kathy Smith | D6: E0003 | E6: ="UPDATE "&$E$3&" SET NEW_EMPLOYEE_ID = '"&D6&"' WHERE LEGACY_EMPLOYEE_ID = '"&B6&"' AND DATA_FOLDER_ID = '"&$A6&"'" -> UPDATE [MAP].[T_TRANS_EMPLOYEE] SET NEW_EMPLOYEE_ID = 'E0003' WHERE LEGACY_EMPLOYEE_ID = 'EE3' AND DATA_FOLDER_ID = 'sampl' | F6: =IF(B6<>D6,"Changed","-") -> Changed | G6: =IF(B6="","Hide","-") -> -

Sheet Inventory Item ID
A1: ="Legacy ERP: "&Controls!$B$2 -> Legacy ERP: Sage 300 CRE | D1: ="New ERP: "&Controls!$B$3 -> New ERP: Sage Intacct
A3: Data Folder ID | B3: Inventory Item | C3: Inventory Item Description | D3: Inventory Item | E3: [MAP].[T_TRANS_ITEM] | F3: Change | G3: hide/show
A4: sampl | B4: 00123546 | C4: Widget A | D4: ITM-001 | E4: ="UPDATE "&$E$3&" SET NEW_ITEM_ID = '"&D4&"' WHERE LEGACY_ITEM_ID = '"&B4&"' AND DATA_FOLDER_ID = '"&$A4&"'" -> UPDATE [MAP].[T_TRANS_ITEM] SET NEW_ITEM_ID = 'ITM-001' WHERE LEGACY_ITEM_ID = '00123546' AND DATA_FOLDER_ID = 'sampl' | F4: =IF(B4<>D4,"Changed","-") -> Changed | G4: =IF(B4="","Hide","-") -> -
A5: sampl | B5: 00123567 | C5: Widget B | D5: ITM-002 | E5: ="UPDATE "&$E$3&" SET NEW_ITEM_ID = '"&D5&"' WHERE LEGACY_ITEM_ID = '"&B5&"' AND DATA_FOLDER_ID = '"&$A5&"'" -> UPDATE [MAP].[T_TRANS_ITEM] SET NEW_ITEM_ID = 'ITM-002' WHERE LEGACY_ITEM_ID = '00123567' AND DATA_FOLDER_ID = 'sampl' | F5: =IF(B5<>D5,"Changed","-") -> Changed | G5: =IF(B5="","Hide","-") -> -
A6: sampl | B6: 00123568 | C6: Widget C | D6: ITM-003 | E6: ="UPDATE "&$E$3&" SET NEW_ITEM_ID = '"&D6&"' WHERE LEGACY_ITEM_ID = '"&B6&"' AND DATA_FOLDER_ID = '"&$A6&"'" -> UPDATE [MAP].[T_TRANS_ITEM] SET NEW_ITEM_ID = 'ITM-003' WHERE LEGACY_ITEM_ID = '00123568' AND DATA_FOLDER_ID = 'sampl' | F6: =IF(B6<>D6,"Changed","-") -> Changed | G6: =IF(B6="","Hide","-") -> -

Sheet Warehouse ID
A1: ="Legacy ERP: "&Controls!$B$2 -> Legacy ERP: Sage 300 CRE | D1: ="New ERP: "&Controls!$B$3 -> New ERP: Sage Intacct
A3: Data Folder ID | B3: Warehouse | C3: Warehouse Description | D3: Warehouse | E3: Location ID | F3: [MAP].[T_TRANS_WAREHOUSE] | G3: Change | H3: hide/show
A4: sampl | B4: OH123 | C4: Ohio Main | D4: 123 | E4: OH | F4: ="UPDATE "&$F$3&" SET NEW_WAREHOUSE_ID = '"&D4&", NEW_LOCATION_ID = '"&E4&"' WHERE LEGACY_WAREHOUSE_ID = '"&B4&"' AND DATA_FOLDER_ID = '"&$A4&"'" -> UPDATE [MAP].[T_TRANS_WAREHOUSE] SET NEW_WAREHOUSE_ID = '123, NEW_LOCATION_ID = 'OH' WHERE LEGACY_WAREHOUSE_ID = 'OH123' AND DATA_FOLDER_ID = 'sampl' | G4: =IF(B4<>D4,"Changed","-") -> Changed | H4: =IF(B4="","Hide","-") -> -
A5: sampl | B5: FL124 | C5: Florida Main | D5: 124 | E5: FL | F5: ="UPDATE "&$F$3&" SET NEW_WAREHOUSE_ID = '"&D5&", NEW_LOCATION_ID = '"&E5&"' WHERE LEGACY_WAREHOUSE_ID = '"&B5&"' AND DATA_FOLDER_ID = '"&$A5&"'" -> UPDATE [MAP].[T_TRANS_WAREHOUSE] SET NEW_WAREHOUSE_ID = '124, NEW_LOCATION_ID = 'FL' WHERE LEGACY_WAREHOUSE_ID = 'FL124' AND DATA_FOLDER_ID = 'sampl' | G5: =IF(B5<>D5,"Changed","-") -> Changed | H5: =IF(B5="","Hide","-") -> -
A6: sampl | B6: IN125 | C6: Indiana Main | D6: 125 | E6: IN | F6: ="UPDATE "&$F$3&" SET NEW_WAREHOUSE_ID = '"&D6&", NEW_LOCATION_ID = '"&E6&"' WHERE LEGACY_WAREHOUSE_ID = '"&B6&"' AND DATA_FOLDER_ID = '"&$A6&"'" -> UPDATE [MAP].[T_TRANS_WAREHOUSE] SET NEW_WAREHOUSE_ID = '125, NEW_LOCATION_ID = 'IN' WHERE LEGACY_WAREHOUSE_ID = 'IN125' AND DATA_FOLDER_ID = 'sampl' | G6: =IF(B6<>D6,"Changed","-") -> Changed | H6: =IF(B6="","Hide","-") -> -
